{
  "인천": [
    {
      "TIM_TIM": "0830",
      "LIN_TIM": 145,
      "COR_NAM": "친선고속(일반)"
    },
    {
      "TIM_TIM": "1320",
      "LIN_TIM": 145,
      "COR_NAM": "친선고속(일반)"
    },
    {
      "TIM_TIM": "1730",
      "LIN_TIM": 145,
      "COR_NAM": "친선고속(일반)"
    }
  ],
  "동서울": [
    {
      "TIM_TIM": "0700",
      "LIN_TIM": 110,
      "COR_NAM": "경기고속(일반)"
    },
    {
      "TIM_TIM": "0900",
      "LIN_TIM": 110,
      "COR_NAM": "경기고속(일반)"
    },
    {
      "TIM_TIM": "1020",
      "LIN_TIM": 110,
      "COR_NAM": "경기고속(일반)"
    },
    {
      "TIM_TIM": "1300",
      "LIN_TIM": 110,
      "COR_NAM": "경기고속(일반)"
    },
    {
      "TIM_TIM": "1500",
      "LIN_TIM": 110,
      "COR_NAM": "경기고속(일반)"
    },
    {
      "TIM_TIM": "1640",
      "LIN_TIM": 110,
      "COR_NAM": "경기고속(일반)"
    }
  ],
  "부천": [
    {
      "TIM_TIM": "1825",
      "LIN_TIM": 170,
      "COR_NAM": "대원고속(일반)"
    }
  ],
  "안양": [
    {
      "TIM_TIM": "1825",
      "LIN_TIM": 140,
      "COR_NAM": "대원고속(일반)"
    }
  ],
  "호계동": [
    {
      "TIM_TIM": "1825",
      "LIN_TIM": 130,
      "COR_NAM": "대원고속(일반)"
    }
  ],
  "고천": [
    {
      "TIM_TIM": "1825",
      "LIN_TIM": 120,
      "COR_NAM": "대원고속(일반)"
    }
  ],
  "충주": [
    {
      "TIM_TIM": "1825",
      "LIN_TIM": 10,
      "COR_NAM": "대원고속(일반)"
    }
  ],
  "일죽": [
    {
      "TIM_TIM": "0700",
      "LIN_TIM": 50,
      "COR_NAM": "경기고속(일반)"
    },
    {
      "TIM_TIM": "0900",
      "LIN_TIM": 50,
      "COR_NAM": "경기고속(일반)"
    },
    {
      "TIM_TIM": "1020",
      "LIN_TIM": 50,
      "COR_NAM": "경기고속(일반)"
    },
    {
      "TIM_TIM": "1300",
      "LIN_TIM": 50,
      "COR_NAM": "경기고속(일반)"
    },
    {
      "TIM_TIM": "1500",
      "LIN_TIM": 50,
      "COR_NAM": "경기고속(일반)"
    },
    {
      "TIM_TIM": "1640",
      "LIN_TIM": 50,
      "COR_NAM": "경기고속(일반)"
    }
  ],
  "안산": [
    {
      "TIM_TIM": "0830",
      "LIN_TIM": 105,
      "COR_NAM": "친선고속(일반)"
    },
    {
      "TIM_TIM": "1320",
      "LIN_TIM": 105,
      "COR_NAM": "친선고속(일반)"
    },
    {
      "TIM_TIM": "1730",
      "LIN_TIM": 105,
      "COR_NAM": "친선고속(일반)"
    }
  ],
  "교통대": [
    {
      "TIM_TIM": "0700",
      "LIN_TIM": 5,
      "COR_NAM": "경기고속(일반)"
    },
    {
      "TIM_TIM": "0900",
      "LIN_TIM": 5,
      "COR_NAM": "경기고속(일반)"
    },
    {
      "TIM_TIM": "1020",
      "LIN_TIM": 5,
      "COR_NAM": "경기고속(일반)"
    },
    {
      "TIM_TIM": "1300",
      "LIN_TIM": 5,
      "COR_NAM": "경기고속(일반)"
    },
    {
      "TIM_TIM": "1500",
      "LIN_TIM": 5,
      "COR_NAM": "경기고속(일반)"
    },
    {
      "TIM_TIM": "1640",
      "LIN_TIM": 5,
      "COR_NAM": "경기고속(일반)"
    }
  ]
}