{
  "신갈(용인)": [
    {
      "TIM_TIM": "0745",
      "LIN_TIM": 70,
      "COR_NAM": "경남여객(일반)"
    },
    {
      "TIM_TIM": "1005",
      "LIN_TIM": 70,
      "COR_NAM": "경남여객(일반)"
    },
    {
      "TIM_TIM": "1300",
      "LIN_TIM": 70,
      "COR_NAM": "경남여객(일반)"
    },
    {
      "TIM_TIM": "1530",
      "LIN_TIM": 70,
      "COR_NAM": "경남여객(일반)"
    },
    {
      "TIM_TIM": "1820",
      "LIN_TIM": 70,
      "COR_NAM": "경남여객(일반)"
    },
    {
      "TIM_TIM": "2105",
      "LIN_TIM": 67,
      "COR_NAM": "경남여객(일반)"
    }
  ],
  "강남대": [
    {
      "TIM_TIM": "0745",
      "LIN_TIM": 90,
      "COR_NAM": "경남여객(일반)"
    },
    {
      "TIM_TIM": "1005",
      "LIN_TIM": 90,
      "COR_NAM": "경남여객(일반)"
    },
    {
      "TIM_TIM": "1300",
      "LIN_TIM": 90,
      "COR_NAM": "경남여객(일반)"
    },
    {
      "TIM_TIM": "1530",
      "LIN_TIM": 90,
      "COR_NAM": "경남여객(일반)"
    },
    {
      "TIM_TIM": "1820",
      "LIN_TIM": 90,
      "COR_NAM": "경남여객(일반)"
    },
    {
      "TIM_TIM": "2105",
      "LIN_TIM": 84,
      "COR_NAM": "경남여객(일반)"
    }
  ],
  "해남": [
    {
      "TIM_TIM": "0820",
      "LIN_TIM": 290,
      "COR_NAM": "경기고속(우등)"
    }
  ],
  "영광": [
    {
      "TIM_TIM": "0830",
      "LIN_TIM": 200,
      "COR_NAM": "경기고속(우등)"
    },
    {
      "TIM_TIM": "1520",
      "LIN_TIM": 200,
      "COR_NAM": "금호고속(우등)"
    }
  ],
  "신평": [
    {
      "TIM_TIM": "0730",
      "LIN_TIM": 79,
      "COR_NAM": "한양고속(우등)"
    },
    {
      "TIM_TIM": "1150",
      "LIN_TIM": 79,
      "COR_NAM": "충남고속(우등)"
    },
    {
      "TIM_TIM": "1700",
      "LIN_TIM": 79,
      "COR_NAM": "충남고속(일반)"
    },
    {
      "TIM_TIM": "1955",
      "LIN_TIM": 79,
      "COR_NAM": "한양고속(우등)"
    }
  ],
  "한서대": [
    {
      "TIM_TIM": "1050",
      "LIN_TIM": 86,
      "COR_NAM": "한양고속(우등)"
    },
    {
      "TIM_TIM": "1530",
      "LIN_TIM": 86,
      "COR_NAM": "충남고속(우등)"
    },
    {
      "TIM_TIM": "1645",
      "LIN_TIM": 86,
      "COR_NAM": "한양고속(우등)"
    },
    {
      "TIM_TIM": "2010",
      "LIN_TIM": 86,
      "COR_NAM": "충남고속(우등)"
    }
  ],
  "함양": [
    {
      "TIM_TIM": "0750",
      "LIN_TIM": 250,
      "COR_NAM": "거창고속(우등)"
    },
    {
      "TIM_TIM": "1200",
      "LIN_TIM": 250,
      "COR_NAM": "거창고속(우등)"
    },
    {
      "TIM_TIM": "1430",
      "LIN_TIM": 250,
      "COR_NAM": "거창고속(우등)"
    },
    {
      "TIM_TIM": "1620",
      "LIN_TIM": 250,
      "COR_NAM": "거창고속(우등)"
    }
  ],
  "점촌": [
    {
      "TIM_TIM": "0730",
      "LIN_TIM": 190,
      "COR_NAM": "대원고속(우등)"
    },
    {
      "TIM_TIM": "1325",
      "LIN_TIM": 190,
      "COR_NAM": "대원고속(우등)"
    },
    {
      "TIM_TIM": "1510",
      "LIN_TIM": 190,
      "COR_NAM": "대원고속(우등)"
    },
    {
      "TIM_TIM": "1715",
      "LIN_TIM": 190,
      "COR_NAM": "대원고속(우등)"
    }
  ],
  "상주": [
    {
      "TIM_TIM": "0730",
      "LIN_TIM": 220,
      "COR_NAM": "대원고속(우등)"
    },
    {
      "TIM_TIM": "1325",
      "LIN_TIM": 220,
      "COR_NAM": "대원고속(우등)"
    },
    {
      "TIM_TIM": "1510",
      "LIN_TIM": 220,
      "COR_NAM": "대원고속(우등)"
    },
    {
      "TIM_TIM": "1715",
      "LIN_TIM": 220,
      "COR_NAM": "대원고속(우등)"
    }
  ],
  "대전청사(선사유적)": [
    {
      "TIM_TIM": "0610",
      "LIN_TIM": 140,
      "COR_NAM": "금남고속(우등)"
    },
    {
      "TIM_TIM": "0710",
      "LIN_TIM": 140,
      "COR_NAM": "금남고속(일반)"
    },
    {
      "TIM_TIM": "0940",
      "LIN_TIM": 140,
      "COR_NAM": "금남고속(우등)"
    },
    {
      "TIM_TIM": "1120",
      "LIN_TIM": 140,
      "COR_NAM": "금남고속(우등)"
    },
    {
      "TIM_TIM": "1300",
      "LIN_TIM": 140,
      "COR_NAM": "금남고속(우등)"
    },
    {
      "TIM_TIM": "1440",
      "LIN_TIM": 140,
      "COR_NAM": "금남고속(우등)"
    },
    {
      "TIM_TIM": "1615",
      "LIN_TIM": 140,
      "COR_NAM": "금남고속(우등)"
    },
    {
      "TIM_TIM": "1710",
      "LIN_TIM": 140,
      "COR_NAM": "금남고속(우등)"
    },
    {
      "TIM_TIM": "1850",
      "LIN_TIM": 140,
      "COR_NAM": "금남고속(우등)"
    },
    {
      "TIM_TIM": "2030",
      "LIN_TIM": 140,
      "COR_NAM": "금남고속(우등)"
    }
  ],
  "영주": [
    {
      "TIM_TIM": "0640",
      "LIN_TIM": 190,
      "COR_NAM": "경북고속(우등)"
    },
    {
      "TIM_TIM": "0745",
      "LIN_TIM": 204,
      "COR_NAM": "경북고속(우등)"
    },
    {
      "TIM_TIM": "0900",
      "LIN_TIM": 204,
      "COR_NAM": "경북고속(우등)"
    },
    {
      "TIM_TIM": "1120",
      "LIN_TIM": 204,
      "COR_NAM": "경북고속(우등)"
    },
    {
      "TIM_TIM": "1230",
      "LIN_TIM": 190,
      "COR_NAM": "경북고속(우등)"
    },
    {
      "TIM_TIM": "1455",
      "LIN_TIM": 204,
      "COR_NAM": "경북고속(우등)"
    },
    {
      "TIM_TIM": "1710",
      "LIN_TIM": 204,
      "COR_NAM": "경북고속(우등)"
    },
    {
      "TIM_TIM": "1830",
      "LIN_TIM": 204,
      "COR_NAM": "경북고속(우등)"
    },
    {
      "TIM_TIM": "1930",
      "LIN_TIM": 204,
      "COR_NAM": "경북고속(우등)"
    }
  ],
  "울진": [
    {
      "TIM_TIM": "1140",
      "LIN_TIM": 515,
      "COR_NAM": "아성고속(우등)"
    }
  ],
  "오산": [
    {
      "TIM_TIM": "0650",
      "LIN_TIM": 100,
      "COR_NAM": "경북고속(우등)"
    },
    {
      "TIM_TIM": "0850",
      "LIN_TIM": 95,
      "COR_NAM": "경북고속(우등)"
    },
    {
      "TIM_TIM": "1100",
      "LIN_TIM": 100,
      "COR_NAM": "경북고속(우등)"
    },
    {
      "TIM_TIM": "1330",
      "LIN_TIM": 100,
      "COR_NAM": "경북고속(우등)"
    },
    {
      "TIM_TIM": "1610",
      "LIN_TIM": 95,
      "COR_NAM": "경북고속(우등)"
    }
  ],
  "가락시장": [
    {
      "TIM_TIM": "0540",
      "LIN_TIM": 60,
      "COR_NAM": "경기고속(일반)"
    },
    {
      "TIM_TIM": "0610",
      "LIN_TIM": 60,
      "COR_NAM": "경기고속(일반)"
    },
    {
      "TIM_TIM": "0635",
      "LIN_TIM": 60,
      "COR_NAM": "경기고속(일반)"
    },
    {
      "TIM_TIM": "0710",
      "LIN_TIM": 60,
      "COR_NAM": "경기고속(일반)"
    },
    {
      "TIM_TIM": "0740",
      "LIN_TIM": 60,
      "COR_NAM": "경기고속(일반)"
    },
    {
      "TIM_TIM": "0810",
      "LIN_TIM": 60,
      "COR_NAM": "경기고속(일반)"
    },
    {
      "TIM_TIM": "0850",
      "LIN_TIM": 60,
      "COR_NAM": "경기고속(일반)"
    },
    {
      "TIM_TIM": "0930",
      "LIN_TIM": 60,
      "COR_NAM": "경기고속(일반)"
    },
    {
      "TIM_TIM": "1030",
      "LIN_TIM": 60,
      "COR_NAM": "경기고속(일반)"
    },
    {
      "TIM_TIM": "1110",
      "LIN_TIM": 60,
      "COR_NAM": "경기고속(일반)"
    },
    {
      "TIM_TIM": "1200",
      "LIN_TIM": 60,
      "COR_NAM": "경기고속(일반)"
    },
    {
      "TIM_TIM": "1240",
      "LIN_TIM": 60,
      "COR_NAM": "경기고속(일반)"
    },
    {
      "TIM_TIM": "1310",
      "LIN_TIM": 60,
      "COR_NAM": "경기고속(일반)"
    },
    {
      "TIM_TIM": "1340",
      "LIN_TIM": 60,
      "COR_NAM": "경기고속(일반)"
    },
    {
      "TIM_TIM": "1440",
      "LIN_TIM": 60,
      "COR_NAM": "경기고속(일반)"
    },
    {
      "TIM_TIM": "1510",
      "LIN_TIM": 60,
      "COR_NAM": "경기고속(일반)"
    },
    {
      "TIM_TIM": "1550",
      "LIN_TIM": 60,
      "COR_NAM": "경기고속(일반)"
    },
    {
      "TIM_TIM": "1630",
      "LIN_TIM": 60,
      "COR_NAM": "경기고속(일반)"
    },
    {
      "TIM_TIM": "1730",
      "LIN_TIM": 60,
      "COR_NAM": "경기고속(일반)"
    },
    {
      "TIM_TIM": "1820",
      "LIN_TIM": 60,
      "COR_NAM": "경기고속(일반)"
    },
    {
      "TIM_TIM": "1900",
      "LIN_TIM": 60,
      "COR_NAM": "경기고속(일반)"
    }
  ],
  "잠실역(중앙)": [
    {
      "TIM_TIM": "0540",
      "LIN_TIM": 70,
      "COR_NAM": "경기고속(일반)"
    },
    {
      "TIM_TIM": "0610",
      "LIN_TIM": 70,
      "COR_NAM": "경기고속(일반)"
    },
    {
      "TIM_TIM": "0635",
      "LIN_TIM": 70,
      "COR_NAM": "경기고속(일반)"
    },
    {
      "TIM_TIM": "0710",
      "LIN_TIM": 70,
      "COR_NAM": "경기고속(일반)"
    },
    {
      "TIM_TIM": "0740",
      "LIN_TIM": 70,
      "COR_NAM": "경기고속(일반)"
    },
    {
      "TIM_TIM": "0810",
      "LIN_TIM": 70,
      "COR_NAM": "경기고속(일반)"
    },
    {
      "TIM_TIM": "0850",
      "LIN_TIM": 70,
      "COR_NAM": "경기고속(일반)"
    },
    {
      "TIM_TIM": "0930",
      "LIN_TIM": 70,
      "COR_NAM": "경기고속(일반)"
    },
    {
      "TIM_TIM": "1030",
      "LIN_TIM": 70,
      "COR_NAM": "경기고속(일반)"
    },
    {
      "TIM_TIM": "1110",
      "LIN_TIM": 70,
      "COR_NAM": "경기고속(일반)"
    },
    {
      "TIM_TIM": "1200",
      "LIN_TIM": 70,
      "COR_NAM": "경기고속(일반)"
    },
    {
      "TIM_TIM": "1240",
      "LIN_TIM": 70,
      "COR_NAM": "경기고속(일반)"
    },
    {
      "TIM_TIM": "1310",
      "LIN_TIM": 70,
      "COR_NAM": "경기고속(일반)"
    },
    {
      "TIM_TIM": "1340",
      "LIN_TIM": 70,
      "COR_NAM": "경기고속(일반)"
    },
    {
      "TIM_TIM": "1440",
      "LIN_TIM": 70,
      "COR_NAM": "경기고속(일반)"
    },
    {
      "TIM_TIM": "1510",
      "LIN_TIM": 70,
      "COR_NAM": "경기고속(일반)"
    },
    {
      "TIM_TIM": "1550",
      "LIN_TIM": 70,
      "COR_NAM": "경기고속(일반)"
    },
    {
      "TIM_TIM": "1630",
      "LIN_TIM": 70,
      "COR_NAM": "경기고속(일반)"
    },
    {
      "TIM_TIM": "1730",
      "LIN_TIM": 70,
      "COR_NAM": "경기고속(일반)"
    },
    {
      "TIM_TIM": "1820",
      "LIN_TIM": 70,
      "COR_NAM": "경기고속(일반)"
    },
    {
      "TIM_TIM": "1900",
      "LIN_TIM": 70,
      "COR_NAM": "경기고속(일반)"
    }
  ],
  "기흥역": [
    {
      "TIM_TIM": "0745",
      "LIN_TIM": 85,
      "COR_NAM": "경남여객(일반)"
    },
    {
      "TIM_TIM": "1005",
      "LIN_TIM": 85,
      "COR_NAM": "경남여객(일반)"
    },
    {
      "TIM_TIM": "1300",
      "LIN_TIM": 85,
      "COR_NAM": "경남여객(일반)"
    },
    {
      "TIM_TIM": "1530",
      "LIN_TIM": 85,
      "COR_NAM": "경남여객(일반)"
    },
    {
      "TIM_TIM": "1820",
      "LIN_TIM": 85,
      "COR_NAM": "경남여객(일반)"
    },
    {
      "TIM_TIM": "2105",
      "LIN_TIM": 77,
      "COR_NAM": "경남여객(일반)"
    }
  ],
  "양평": [
    {
      "TIM_TIM": "0655",
      "LIN_TIM": 100,
      "COR_NAM": "금강고속(일반)"
    },
    {
      "TIM_TIM": "1100",
      "LIN_TIM": 100,
      "COR_NAM": "금강고속(일반)"
    },
    {
      "TIM_TIM": "1300",
      "LIN_TIM": 100,
      "COR_NAM": "금강고속(일반)"
    },
    {
      "TIM_TIM": "1520",
      "LIN_TIM": 100,
      "COR_NAM": "금강고속(일반)"
    },
    {
      "TIM_TIM": "1700",
      "LIN_TIM": 100,
      "COR_NAM": "금강고속(일반)"
    }
  ],
  "가천대": [
    {
      "TIM_TIM": "0540",
      "LIN_TIM": 45,
      "COR_NAM": "경기고속(일반)"
    },
    {
      "TIM_TIM": "0610",
      "LIN_TIM": 45,
      "COR_NAM": "경기고속(일반)"
    },
    {
      "TIM_TIM": "0635",
      "LIN_TIM": 45,
      "COR_NAM": "경기고속(일반)"
    },
    {
      "TIM_TIM": "0710",
      "LIN_TIM": 45,
      "COR_NAM": "경기고속(일반)"
    },
    {
      "TIM_TIM": "0740",
      "LIN_TIM": 45,
      "COR_NAM": "경기고속(일반)"
    },
    {
      "TIM_TIM": "0810",
      "LIN_TIM": 45,
      "COR_NAM": "경기고속(일반)"
    },
    {
      "TIM_TIM": "0850",
      "LIN_TIM": 45,
      "COR_NAM": "경기고속(일반)"
    },
    {
      "TIM_TIM": "0930",
      "LIN_TIM": 45,
      "COR_NAM": "경기고속(일반)"
    },
    {
      "TIM_TIM": "1030",
      "LIN_TIM": 45,
      "COR_NAM": "경기고속(일반)"
    },
    {
      "TIM_TIM": "1110",
      "LIN_TIM": 45,
      "COR_NAM": "경기고속(일반)"
    },
    {
      "TIM_TIM": "1200",
      "LIN_TIM": 45,
      "COR_NAM": "경기고속(일반)"
    },
    {
      "TIM_TIM": "1240",
      "LIN_TIM": 45,
      "COR_NAM": "경기고속(일반)"
    },
    {
      "TIM_TIM": "1310",
      "LIN_TIM": 45,
      "COR_NAM": "경기고속(일반)"
    },
    {
      "TIM_TIM": "1340",
      "LIN_TIM": 45,
      "COR_NAM": "경기고속(일반)"
    },
    {
      "TIM_TIM": "1440",
      "LIN_TIM": 45,
      "COR_NAM": "경기고속(일반)"
    },
    {
      "TIM_TIM": "1510",
      "LIN_TIM": 45,
      "COR_NAM": "경기고속(일반)"
    },
    {
      "TIM_TIM": "1550",
      "LIN_TIM": 45,
      "COR_NAM": "경기고속(일반)"
    },
    {
      "TIM_TIM": "1630",
      "LIN_TIM": 45,
      "COR_NAM": "경기고속(일반)"
    },
    {
      "TIM_TIM": "1730",
      "LIN_TIM": 45,
      "COR_NAM": "경기고속(일반)"
    },
    {
      "TIM_TIM": "1820",
      "LIN_TIM": 45,
      "COR_NAM": "경기고속(일반)"
    },
    {
      "TIM_TIM": "1900",
      "LIN_TIM": 45,
      "COR_NAM": "경기고속(일반)"
    }
  ],
  "에버랜드": [
    {
      "TIM_TIM": "0745",
      "LIN_TIM": 120,
      "COR_NAM": "경남여객(일반)"
    },
    {
      "TIM_TIM": "1005",
      "LIN_TIM": 120,
      "COR_NAM": "경남여객(일반)"
    },
    {
      "TIM_TIM": "1300",
      "LIN_TIM": 120,
      "COR_NAM": "경남여객(일반)"
    },
    {
      "TIM_TIM": "1530",
      "LIN_TIM": 120,
      "COR_NAM": "경남여객(일반)"
    },
    {
      "TIM_TIM": "1820",
      "LIN_TIM": 120,
      "COR_NAM": "경남여객(일반)"
    }
  ],
  "무안(전남)": [
    {
      "TIM_TIM": "0830",
      "LIN_TIM": 255,
      "COR_NAM": "경기고속(우등)"
    },
    {
      "TIM_TIM": "1520",
      "LIN_TIM": 255,
      "COR_NAM": "금호고속(우등)"
    }
  ],
  "군산": [
    {
      "TIM_TIM": "0830",
      "LIN_TIM": 150,
      "COR_NAM": "전북고속(일반)"
    },
    {
      "TIM_TIM": "1110",
      "LIN_TIM": 150,
      "COR_NAM": "전북고속(우등)"
    },
    {
      "TIM_TIM": "1210",
      "LIN_TIM": 150,
      "COR_NAM": "호남고속(일반)"
    },
    {
      "TIM_TIM": "1330",
      "LIN_TIM": 150,
      "COR_NAM": "호남고속(우등)"
    },
    {
      "TIM_TIM": "1450",
      "LIN_TIM": 150,
      "COR_NAM": "전북고속(우등)"
    },
    {
      "TIM_TIM": "1610",
      "LIN_TIM": 150,
      "COR_NAM": "전북고속(우등)"
    },
    {
      "TIM_TIM": "1800",
      "LIN_TIM": 150,
      "COR_NAM": "전북고속(일반)"
    },
    {
      "TIM_TIM": "1920",
      "LIN_TIM": 150,
      "COR_NAM": "전북고속(우등)"
    }
  ],
  "창원": [
    {
      "TIM_TIM": "0910",
      "LIN_TIM": 300,
      "COR_NAM": "대원고속(우등)"
    },
    {
      "TIM_TIM": "1300",
      "LIN_TIM": 300,
      "COR_NAM": "경남고속뉴부산관광(우등)"
    },
    {
      "TIM_TIM": "1600",
      "LIN_TIM": 300,
      "COR_NAM": "대원고속(우등)"
    },
    {
      "TIM_TIM": "1850",
      "LIN_TIM": 300,
      "COR_NAM": "경남고속뉴부산관광(우등)"
    },
    {
      "TIM_TIM": "2330",
      "LIN_TIM": 300,
      "COR_NAM": "천일여객(심야우등)"
    }
  ],
  "홍성": [
    {
      "TIM_TIM": "0755",
      "LIN_TIM": 148,
      "COR_NAM": "충남고속(일반)"
    },
    {
      "TIM_TIM": "1640",
      "LIN_TIM": 148,
      "COR_NAM": "충남고속(일반)"
    }
  ],
  "신양": [
    {
      "TIM_TIM": "0830",
      "LIN_TIM": 130,
      "COR_NAM": "충남고속(우등)"
    },
    {
      "TIM_TIM": "1350",
      "LIN_TIM": 110,
      "COR_NAM": "충남고속(우등)"
    },
    {
      "TIM_TIM": "1840",
      "LIN_TIM": 130,
      "COR_NAM": "충남고속(우등)"
    }
  ],
  "광혜원": [
    {
      "TIM_TIM": "0600",
      "LIN_TIM": 197,
      "COR_NAM": "대원고속(일반)"
    },
    {
      "TIM_TIM": "1200",
      "LIN_TIM": 197,
      "COR_NAM": "경일여객(일반)"
    },
    {
      "TIM_TIM": "1420",
      "LIN_TIM": 197,
      "COR_NAM": "친선고속(일반)"
    },
    {
      "TIM_TIM": "1600",
      "LIN_TIM": 197,
      "COR_NAM": "대원고속(일반)"
    }
  ],
  "진천": [
    {
      "TIM_TIM": "0600",
      "LIN_TIM": 217,
      "COR_NAM": "대원고속(일반)"
    },
    {
      "TIM_TIM": "1200",
      "LIN_TIM": 217,
      "COR_NAM": "경일여객(일반)"
    },
    {
      "TIM_TIM": "1420",
      "LIN_TIM": 217,
      "COR_NAM": "친선고속(일반)"
    },
    {
      "TIM_TIM": "1600",
      "LIN_TIM": 217,
      "COR_NAM": "대원고속(일반)"
    }
  ],
  "청주": [
    {
      "TIM_TIM": "0630",
      "LIN_TIM": 120,
      "COR_NAM": "금남고속(우등)"
    },
    {
      "TIM_TIM": "0750",
      "LIN_TIM": 120,
      "COR_NAM": "금남고속(우등)"
    },
    {
      "TIM_TIM": "0920",
      "LIN_TIM": 120,
      "COR_NAM": "금남고속(우등)"
    },
    {
      "TIM_TIM": "1030",
      "LIN_TIM": 120,
      "COR_NAM": "금남고속(우등)"
    },
    {
      "TIM_TIM": "1130",
      "LIN_TIM": 120,
      "COR_NAM": "금남고속(우등)"
    },
    {
      "TIM_TIM": "1200",
      "LIN_TIM": 120,
      "COR_NAM": "금남고속(우등)"
    },
    {
      "TIM_TIM": "1300",
      "LIN_TIM": 120,
      "COR_NAM": "금남고속(우등)"
    },
    {
      "TIM_TIM": "1345",
      "LIN_TIM": 120,
      "COR_NAM": "금남고속(우등)"
    },
    {
      "TIM_TIM": "1440",
      "LIN_TIM": 120,
      "COR_NAM": "금남고속(우등)"
    },
    {
      "TIM_TIM": "1550",
      "LIN_TIM": 120,
      "COR_NAM": "금남고속(우등)"
    },
    {
      "TIM_TIM": "1650",
      "LIN_TIM": 120,
      "COR_NAM": "금남고속(우등)"
    },
    {
      "TIM_TIM": "1730",
      "LIN_TIM": 120,
      "COR_NAM": "금남고속(우등)"
    },
    {
      "TIM_TIM": "1800",
      "LIN_TIM": 120,
      "COR_NAM": "대성고속(우등)"
    },
    {
      "TIM_TIM": "1830",
      "LIN_TIM": 120,
      "COR_NAM": "금남고속(우등)"
    },
    {
      "TIM_TIM": "1920",
      "LIN_TIM": 120,
      "COR_NAM": "금남고속(우등)"
    },
    {
      "TIM_TIM": "2010",
      "LIN_TIM": 120,
      "COR_NAM": "금남고속(우등)"
    },
    {
      "TIM_TIM": "2040",
      "LIN_TIM": 120,
      "COR_NAM": "금남고속(우등)"
    }
  ],
  "춘천": [
    {
      "TIM_TIM": "0640",
      "LIN_TIM": 160,
      "COR_NAM": "강원고속(우등)"
    },
    {
      "TIM_TIM": "0840",
      "LIN_TIM": 160,
      "COR_NAM": "강원고속(우등)"
    },
    {
      "TIM_TIM": "1310",
      "LIN_TIM": 160,
      "COR_NAM": "강원고속(우등)"
    },
    {
      "TIM_TIM": "1510",
      "LIN_TIM": 160,
      "COR_NAM": "강원고속(우등)"
    },
    {
      "TIM_TIM": "1710",
      "LIN_TIM": 160,
      "COR_NAM": "강원고속(우등)"
    }
  ],
  "강촌": [
    {
      "TIM_TIM": "0640",
      "LIN_TIM": 130,
      "COR_NAM": "강원고속(우등)"
    },
    {
      "TIM_TIM": "0840",
      "LIN_TIM": 130,
      "COR_NAM": "강원고속(우등)"
    },
    {
      "TIM_TIM": "1310",
      "LIN_TIM": 130,
      "COR_NAM": "강원고속(우등)"
    },
    {
      "TIM_TIM": "1510",
      "LIN_TIM": 130,
      "COR_NAM": "강원고속(우등)"
    },
    {
      "TIM_TIM": "1710",
      "LIN_TIM": 130,
      "COR_NAM": "강원고속(우등)"
    }
  ],
  "동서울": [
    {
      "TIM_TIM": "0540",
      "LIN_TIM": 85,
      "COR_NAM": "경기고속(일반)"
    },
    {
      "TIM_TIM": "0610",
      "LIN_TIM": 85,
      "COR_NAM": "경기고속(일반)"
    },
    {
      "TIM_TIM": "0635",
      "LIN_TIM": 85,
      "COR_NAM": "경기고속(일반)"
    },
    {
      "TIM_TIM": "0710",
      "LIN_TIM": 85,
      "COR_NAM": "경기고속(일반)"
    },
    {
      "TIM_TIM": "0740",
      "LIN_TIM": 85,
      "COR_NAM": "경기고속(일반)"
    },
    {
      "TIM_TIM": "0810",
      "LIN_TIM": 85,
      "COR_NAM": "경기고속(일반)"
    },
    {
      "TIM_TIM": "0850",
      "LIN_TIM": 85,
      "COR_NAM": "경기고속(일반)"
    },
    {
      "TIM_TIM": "0930",
      "LIN_TIM": 85,
      "COR_NAM": "경기고속(일반)"
    },
    {
      "TIM_TIM": "1030",
      "LIN_TIM": 85,
      "COR_NAM": "경기고속(일반)"
    },
    {
      "TIM_TIM": "1110",
      "LIN_TIM": 85,
      "COR_NAM": "경기고속(일반)"
    },
    {
      "TIM_TIM": "1200",
      "LIN_TIM": 85,
      "COR_NAM": "경기고속(일반)"
    },
    {
      "TIM_TIM": "1240",
      "LIN_TIM": 85,
      "COR_NAM": "경기고속(일반)"
    },
    {
      "TIM_TIM": "1310",
      "LIN_TIM": 85,
      "COR_NAM": "경기고속(일반)"
    },
    {
      "TIM_TIM": "1340",
      "LIN_TIM": 85,
      "COR_NAM": "경기고속(일반)"
    },
    {
      "TIM_TIM": "1440",
      "LIN_TIM": 85,
      "COR_NAM": "경기고속(일반)"
    },
    {
      "TIM_TIM": "1510",
      "LIN_TIM": 85,
      "COR_NAM": "경기고속(일반)"
    },
    {
      "TIM_TIM": "1550",
      "LIN_TIM": 85,
      "COR_NAM": "경기고속(일반)"
    },
    {
      "TIM_TIM": "1630",
      "LIN_TIM": 85,
      "COR_NAM": "경기고속(일반)"
    },
    {
      "TIM_TIM": "1730",
      "LIN_TIM": 85,
      "COR_NAM": "경기고속(일반)"
    },
    {
      "TIM_TIM": "1820",
      "LIN_TIM": 85,
      "COR_NAM": "경기고속(일반)"
    },
    {
      "TIM_TIM": "1900",
      "LIN_TIM": 85,
      "COR_NAM": "경기고속(일반)"
    }
  ],
  "태백": [
    {
      "TIM_TIM": "0610",
      "LIN_TIM": 230,
      "COR_NAM": "경기고속(프리미엄)"
    },
    {
      "TIM_TIM": "1130",
      "LIN_TIM": 230,
      "COR_NAM": "경기고속(프리미엄)"
    },
    {
      "TIM_TIM": "1520",
      "LIN_TIM": 230,
      "COR_NAM": "경기고속(우등)"
    },
    {
      "TIM_TIM": "1750",
      "LIN_TIM": 230,
      "COR_NAM": "경기고속(프리미엄)"
    }
  ],
  "청평": [
    {
      "TIM_TIM": "0640",
      "LIN_TIM": 85,
      "COR_NAM": "강원고속(우등)"
    },
    {
      "TIM_TIM": "0840",
      "LIN_TIM": 85,
      "COR_NAM": "강원고속(우등)"
    },
    {
      "TIM_TIM": "1310",
      "LIN_TIM": 85,
      "COR_NAM": "강원고속(우등)"
    },
    {
      "TIM_TIM": "1510",
      "LIN_TIM": 85,
      "COR_NAM": "강원고속(우등)"
    },
    {
      "TIM_TIM": "1710",
      "LIN_TIM": 85,
      "COR_NAM": "강원고속(우등)"
    }
  ],
  "부천": [
    {
      "TIM_TIM": "1320",
      "LIN_TIM": 40,
      "COR_NAM": "금호고속(우등)"
    }
  ],
  "신창": [
    {
      "TIM_TIM": "0755",
      "LIN_TIM": 84,
      "COR_NAM": "충남고속(일반)"
    },
    {
      "TIM_TIM": "0830",
      "LIN_TIM": 84,
      "COR_NAM": "충남고속(우등)"
    },
    {
      "TIM_TIM": "1640",
      "LIN_TIM": 84,
      "COR_NAM": "충남고속(일반)"
    },
    {
      "TIM_TIM": "1840",
      "LIN_TIM": 84,
      "COR_NAM": "충남고속(우등)"
    }
  ],
  "제천": [
    {
      "TIM_TIM": "0630",
      "LIN_TIM": 190,
      "COR_NAM": "대원고속(일반)"
    },
    {
      "TIM_TIM": "1100",
      "LIN_TIM": 150,
      "COR_NAM": "대원고속(일반)"
    },
    {
      "TIM_TIM": "1250",
      "LIN_TIM": 190,
      "COR_NAM": "대원고속(일반)"
    },
    {
      "TIM_TIM": "1850",
      "LIN_TIM": 150,
      "COR_NAM": "대원고속(일반)"
    }
  ],
  "내포": [
    {
      "TIM_TIM": "0755",
      "LIN_TIM": 132,
      "COR_NAM": "충남고속(일반)"
    },
    {
      "TIM_TIM": "1640",
      "LIN_TIM": 132,
      "COR_NAM": "충남고속(일반)"
    }
  ],
  "효령": [
    {
      "TIM_TIM": "0850",
      "LIN_TIM": 294,
      "COR_NAM": "경북고속(우등)"
    },
    {
      "TIM_TIM": "1610",
      "LIN_TIM": 294,
      "COR_NAM": "경북고속(우등)"
    }
  ],
  "구미복지": [
    {
      "TIM_TIM": "0650",
      "LIN_TIM": 258,
      "COR_NAM": "경북고속(우등)"
    },
    {
      "TIM_TIM": "1330",
      "LIN_TIM": 258,
      "COR_NAM": "경북고속(우등)"
    }
  ],
  "구미인동": [
    {
      "TIM_TIM": "0850",
      "LIN_TIM": 263,
      "COR_NAM": "경북고속(우등)"
    },
    {
      "TIM_TIM": "1610",
      "LIN_TIM": 263,
      "COR_NAM": "경북고속(우등)"
    }
  ],
  "울산신복": [
    {
      "TIM_TIM": "0930",
      "LIN_TIM": 325,
      "COR_NAM": "아성고속(우등)"
    },
    {
      "TIM_TIM": "1310",
      "LIN_TIM": 325,
      "COR_NAM": "천마고속(우등)"
    },
    {
      "TIM_TIM": "1450",
      "LIN_TIM": 325,
      "COR_NAM": "경기고속(우등)"
    },
    {
      "TIM_TIM": "1640",
      "LIN_TIM": 325,
      "COR_NAM": "아성고속(우등)"
    },
    {
      "TIM_TIM": "2359",
      "LIN_TIM": 325,
      "COR_NAM": "아성고속(심야우등)"
    }
  ],
  "단촌": [
    {
      "TIM_TIM": "0850",
      "LIN_TIM": 338,
      "COR_NAM": "경북고속(우등)"
    },
    {
      "TIM_TIM": "1610",
      "LIN_TIM": 338,
      "COR_NAM": "경북고속(우등)"
    }
  ],
  "의성": [
    {
      "TIM_TIM": "0850",
      "LIN_TIM": 326,
      "COR_NAM": "경북고속(우등)"
    },
    {
      "TIM_TIM": "1610",
      "LIN_TIM": 326,
      "COR_NAM": "경북고속(우등)"
    }
  ],
  "아주대": [
    {
      "TIM_TIM": "0745",
      "LIN_TIM": 50,
      "COR_NAM": "경남여객(일반)"
    },
    {
      "TIM_TIM": "1300",
      "LIN_TIM": 50,
      "COR_NAM": "경남여객(일반)"
    },
    {
      "TIM_TIM": "1820",
      "LIN_TIM": 50,
      "COR_NAM": "경남여객(일반)"
    }
  ],
  "고흥": [
    {
      "TIM_TIM": "1430",
      "LIN_TIM": 310,
      "COR_NAM": "동방고속(우등)"
    }
  ],
  "동아방송대": [
    {
      "TIM_TIM": "0630",
      "LIN_TIM": 110,
      "COR_NAM": "대원고속(일반)"
    },
    {
      "TIM_TIM": "0800",
      "LIN_TIM": 110,
      "COR_NAM": "대원고속(일반)"
    },
    {
      "TIM_TIM": "1035",
      "LIN_TIM": 110,
      "COR_NAM": "대원고속(일반)"
    },
    {
      "TIM_TIM": "1300",
      "LIN_TIM": 111,
      "COR_NAM": "대원고속(일반)"
    },
    {
      "TIM_TIM": "1400",
      "LIN_TIM": 111,
      "COR_NAM": "대원고속(일반)"
    },
    {
      "TIM_TIM": "1620",
      "LIN_TIM": 111,
      "COR_NAM": "대원고속(일반)"
    },
    {
      "TIM_TIM": "1910",
      "LIN_TIM": 110,
      "COR_NAM": "대원고속(일반)"
    }
  ],
  "안양": [
    {
      "TIM_TIM": "0640",
      "LIN_TIM": 20,
      "COR_NAM": "강원고속(우등)"
    },
    {
      "TIM_TIM": "0840",
      "LIN_TIM": 20,
      "COR_NAM": "강원고속(우등)"
    },
    {
      "TIM_TIM": "1310",
      "LIN_TIM": 20,
      "COR_NAM": "강원고속(우등)"
    },
    {
      "TIM_TIM": "1510",
      "LIN_TIM": 20,
      "COR_NAM": "강원고속(우등)"
    },
    {
      "TIM_TIM": "1710",
      "LIN_TIM": 20,
      "COR_NAM": "강원고속(우등)"
    }
  ],
  "범계": [
    {
      "TIM_TIM": "1005",
      "LIN_TIM": 30,
      "COR_NAM": "경남여객(일반)"
    },
    {
      "TIM_TIM": "1530",
      "LIN_TIM": 30,
      "COR_NAM": "경남여객(일반)"
    },
    {
      "TIM_TIM": "2105",
      "LIN_TIM": 31,
      "COR_NAM": "경남여객(일반)"
    }
  ],
  "호계동": [
    {
      "TIM_TIM": "0640",
      "LIN_TIM": 30,
      "COR_NAM": "강원고속(우등)"
    },
    {
      "TIM_TIM": "0840",
      "LIN_TIM": 30,
      "COR_NAM": "강원고속(우등)"
    },
    {
      "TIM_TIM": "1310",
      "LIN_TIM": 30,
      "COR_NAM": "강원고속(우등)"
    },
    {
      "TIM_TIM": "1510",
      "LIN_TIM": 30,
      "COR_NAM": "강원고속(우등)"
    },
    {
      "TIM_TIM": "1710",
      "LIN_TIM": 30,
      "COR_NAM": "강원고속(우등)"
    }
  ],
  "우만동": [
    {
      "TIM_TIM": "0600",
      "LIN_TIM": 107,
      "COR_NAM": "대원고속(일반)"
    },
    {
      "TIM_TIM": "1200",
      "LIN_TIM": 107,
      "COR_NAM": "경일여객(일반)"
    },
    {
      "TIM_TIM": "1420",
      "LIN_TIM": 107,
      "COR_NAM": "친선고속(일반)"
    },
    {
      "TIM_TIM": "1600",
      "LIN_TIM": 107,
      "COR_NAM": "대원고속(일반)"
    }
  ],
  "서수원": [
    {
      "TIM_TIM": "0600",
      "LIN_TIM": 70,
      "COR_NAM": "대원고속(일반)"
    },
    {
      "TIM_TIM": "1200",
      "LIN_TIM": 70,
      "COR_NAM": "경일여객(일반)"
    },
    {
      "TIM_TIM": "1420",
      "LIN_TIM": 70,
      "COR_NAM": "친선고속(일반)"
    },
    {
      "TIM_TIM": "1600",
      "LIN_TIM": 70,
      "COR_NAM": "대원고속(일반)"
    }
  ],
  "영통입구": [
    {
      "TIM_TIM": "0745",
      "LIN_TIM": 60,
      "COR_NAM": "경남여객(일반)"
    },
    {
      "TIM_TIM": "1300",
      "LIN_TIM": 60,
      "COR_NAM": "경남여객(일반)"
    },
    {
      "TIM_TIM": "1820",
      "LIN_TIM": 60,
      "COR_NAM": "경남여객(일반)"
    }
  ],
  "완도": [
    {
      "TIM_TIM": "0820",
      "LIN_TIM": 335,
      "COR_NAM": "경기고속(우등)"
    }
  ],
  "광양": [
    {
      "TIM_TIM": "1500",
      "LIN_TIM": 270,
      "COR_NAM": "경기고속(우등)"
    }
  ],
  "김제": [
    {
      "TIM_TIM": "1520",
      "LIN_TIM": 180,
      "COR_NAM": "호남고속(우등)"
    }
  ],
  "문경": [
    {
      "TIM_TIM": "0730",
      "LIN_TIM": 160,
      "COR_NAM": "대원고속(우등)"
    },
    {
      "TIM_TIM": "1325",
      "LIN_TIM": 160,
      "COR_NAM": "대원고속(우등)"
    },
    {
      "TIM_TIM": "1510",
      "LIN_TIM": 160,
      "COR_NAM": "대원고속(우등)"
    },
    {
      "TIM_TIM": "1715",
      "LIN_TIM": 160,
      "COR_NAM": "대원고속(우등)"
    }
  ],
  "당진": [
    {
      "TIM_TIM": "0640",
      "LIN_TIM": 82,
      "COR_NAM": "충남고속(우등)"
    },
    {
      "TIM_TIM": "0730",
      "LIN_TIM": 99,
      "COR_NAM": "한양고속(우등)"
    },
    {
      "TIM_TIM": "0820",
      "LIN_TIM": 82,
      "COR_NAM": "충남고속(우등)"
    },
    {
      "TIM_TIM": "0910",
      "LIN_TIM": 82,
      "COR_NAM": "한양고속(우등)"
    },
    {
      "TIM_TIM": "1000",
      "LIN_TIM": 82,
      "COR_NAM": "충남고속(우등)"
    },
    {
      "TIM_TIM": "1055",
      "LIN_TIM": 82,
      "COR_NAM": "한양고속(우등)"
    },
    {
      "TIM_TIM": "1150",
      "LIN_TIM": 99,
      "COR_NAM": "충남고속(우등)"
    },
    {
      "TIM_TIM": "1240",
      "LIN_TIM": 82,
      "COR_NAM": "한양고속(우등)"
    },
    {
      "TIM_TIM": "1330",
      "LIN_TIM": 82,
      "COR_NAM": "충남고속(우등)"
    },
    {
      "TIM_TIM": "1420",
      "LIN_TIM": 82,
      "COR_NAM": "한양고속(우등)"
    },
    {
      "TIM_TIM": "1515",
      "LIN_TIM": 82,
      "COR_NAM": "충남고속(우등)"
    },
    {
      "TIM_TIM": "1610",
      "LIN_TIM": 82,
      "COR_NAM": "한양고속(우등)"
    },
    {
      "TIM_TIM": "1700",
      "LIN_TIM": 99,
      "COR_NAM": "충남고속(일반)"
    },
    {
      "TIM_TIM": "1750",
      "LIN_TIM": 82,
      "COR_NAM": "한양고속(우등)"
    },
    {
      "TIM_TIM": "1850",
      "LIN_TIM": 82,
      "COR_NAM": "충남고속(우등)"
    },
    {
      "TIM_TIM": "1955",
      "LIN_TIM": 99,
      "COR_NAM": "한양고속(우등)"
    },
    {
      "TIM_TIM": "2100",
      "LIN_TIM": 82,
      "COR_NAM": "충남고속(우등)"
    }
  ],
  "광천(충남)": [
    {
      "TIM_TIM": "0755",
      "LIN_TIM": 168,
      "COR_NAM": "충남고속(일반)"
    },
    {
      "TIM_TIM": "1640",
      "LIN_TIM": 168,
      "COR_NAM": "충남고속(일반)"
    }
  ],
  "포항": [
    {
      "TIM_TIM": "1000",
      "LIN_TIM": 310,
      "COR_NAM": "아성고속(우등)"
    },
    {
      "TIM_TIM": "1140",
      "LIN_TIM": 350,
      "COR_NAM": "아성고속(우등)"
    },
    {
      "TIM_TIM": "1400",
      "LIN_TIM": 310,
      "COR_NAM": "아성고속(우등)"
    },
    {
      "TIM_TIM": "1600",
      "LIN_TIM": 310,
      "COR_NAM": "천마고속(우등)"
    },
    {
      "TIM_TIM": "1810",
      "LIN_TIM": 310,
      "COR_NAM": "경기고속(우등)"
    },
    {
      "TIM_TIM": "2359",
      "LIN_TIM": 335,
      "COR_NAM": "천마고속(심야우등)"
    }
  ],
  "구미": [
    {
      "TIM_TIM": "0650",
      "LIN_TIM": 250,
      "COR_NAM": "경북고속(우등)"
    },
    {
      "TIM_TIM": "0850",
      "LIN_TIM": 245,
      "COR_NAM": "경북고속(우등)"
    },
    {
      "TIM_TIM": "1100",
      "LIN_TIM": 250,
      "COR_NAM": "경북고속(우등)"
    },
    {
      "TIM_TIM": "1330",
      "LIN_TIM": 250,
      "COR_NAM": "경북고속(우등)"
    },
    {
      "TIM_TIM": "1610",
      "LIN_TIM": 245,
      "COR_NAM": "경북고속(우등)"
    }
  ],
  "구미공단": [
    {
      "TIM_TIM": "0650",
      "LIN_TIM": 255,
      "COR_NAM": "경북고속(우등)"
    },
    {
      "TIM_TIM": "1330",
      "LIN_TIM": 255,
      "COR_NAM": "경북고속(우등)"
    }
  ],
  "풍기IC": [
    {
      "TIM_TIM": "0640",
      "LIN_TIM": 180,
      "COR_NAM": "경북고속(우등)"
    },
    {
      "TIM_TIM": "0745",
      "LIN_TIM": 190,
      "COR_NAM": "경북고속(우등)"
    },
    {
      "TIM_TIM": "0900",
      "LIN_TIM": 190,
      "COR_NAM": "경북고속(우등)"
    },
    {
      "TIM_TIM": "1120",
      "LIN_TIM": 190,
      "COR_NAM": "경북고속(우등)"
    },
    {
      "TIM_TIM": "1230",
      "LIN_TIM": 180,
      "COR_NAM": "경북고속(우등)"
    },
    {
      "TIM_TIM": "1455",
      "LIN_TIM": 190,
      "COR_NAM": "경북고속(우등)"
    },
    {
      "TIM_TIM": "1710",
      "LIN_TIM": 190,
      "COR_NAM": "경북고속(우등)"
    },
    {
      "TIM_TIM": "1830",
      "LIN_TIM": 190,
      "COR_NAM": "경북고속(우등)"
    },
    {
      "TIM_TIM": "1930",
      "LIN_TIM": 190,
      "COR_NAM": "경북고속(우등)"
    }
  ],
  "평해": [
    {
      "TIM_TIM": "1140",
      "LIN_TIM": 472,
      "COR_NAM": "아성고속(우등)"
    }
  ],
  "홍천": [
    {
      "TIM_TIM": "0655",
      "LIN_TIM": 150,
      "COR_NAM": "금강고속(일반)"
    },
    {
      "TIM_TIM": "1100",
      "LIN_TIM": 150,
      "COR_NAM": "금강고속(일반)"
    },
    {
      "TIM_TIM": "1300",
      "LIN_TIM": 150,
      "COR_NAM": "금강고속(일반)"
    },
    {
      "TIM_TIM": "1520",
      "LIN_TIM": 150,
      "COR_NAM": "금강고속(일반)"
    },
    {
      "TIM_TIM": "1700",
      "LIN_TIM": 150,
      "COR_NAM": "금강고속(일반)"
    }
  ],
  "풍림아파트(안성)": [
    {
      "TIM_TIM": "0630",
      "LIN_TIM": 60,
      "COR_NAM": "대원고속(일반)"
    },
    {
      "TIM_TIM": "0800",
      "LIN_TIM": 60,
      "COR_NAM": "대원고속(일반)"
    },
    {
      "TIM_TIM": "1035",
      "LIN_TIM": 60,
      "COR_NAM": "대원고속(일반)"
    },
    {
      "TIM_TIM": "1300",
      "LIN_TIM": 72,
      "COR_NAM": "대원고속(일반)"
    },
    {
      "TIM_TIM": "1400",
      "LIN_TIM": 72,
      "COR_NAM": "대원고속(일반)"
    },
    {
      "TIM_TIM": "1620",
      "LIN_TIM": 72,
      "COR_NAM": "대원고속(일반)"
    },
    {
      "TIM_TIM": "1910",
      "LIN_TIM": 60,
      "COR_NAM": "대원고속(일반)"
    }
  ],
  "가평": [
    {
      "TIM_TIM": "0640",
      "LIN_TIM": 110,
      "COR_NAM": "강원고속(우등)"
    },
    {
      "TIM_TIM": "0840",
      "LIN_TIM": 110,
      "COR_NAM": "강원고속(우등)"
    },
    {
      "TIM_TIM": "1310",
      "LIN_TIM": 110,
      "COR_NAM": "강원고속(우등)"
    },
    {
      "TIM_TIM": "1510",
      "LIN_TIM": 110,
      "COR_NAM": "강원고속(우등)"
    },
    {
      "TIM_TIM": "1710",
      "LIN_TIM": 110,
      "COR_NAM": "강원고속(우등)"
    }
  ],
  "하남BRT": [
    {
      "TIM_TIM": "0655",
      "LIN_TIM": 75,
      "COR_NAM": "금강고속(일반)"
    },
    {
      "TIM_TIM": "1100",
      "LIN_TIM": 75,
      "COR_NAM": "금강고속(일반)"
    },
    {
      "TIM_TIM": "1300",
      "LIN_TIM": 75,
      "COR_NAM": "금강고속(일반)"
    },
    {
      "TIM_TIM": "1520",
      "LIN_TIM": 75,
      "COR_NAM": "금강고속(일반)"
    },
    {
      "TIM_TIM": "1700",
      "LIN_TIM": 75,
      "COR_NAM": "금강고속(일반)"
    }
  ],
  "모란시장": [
    {
      "TIM_TIM": "0530",
      "LIN_TIM": 50,
      "COR_NAM": "대원고속(일반)"
    },
    {
      "TIM_TIM": "0610",
      "LIN_TIM": 50,
      "COR_NAM": "대원고속(일반)"
    },
    {
      "TIM_TIM": "0650",
      "LIN_TIM": 50,
      "COR_NAM": "대원고속(일반)"
    },
    {
      "TIM_TIM": "0730",
      "LIN_TIM": 50,
      "COR_NAM": "대원고속(일반)"
    },
    {
      "TIM_TIM": "0830",
      "LIN_TIM": 50,
      "COR_NAM": "대원고속(일반)"
    },
    {
      "TIM_TIM": "0900",
      "LIN_TIM": 50,
      "COR_NAM": "대원고속(일반)"
    },
    {
      "TIM_TIM": "0930",
      "LIN_TIM": 50,
      "COR_NAM": "대원고속(일반)"
    },
    {
      "TIM_TIM": "1010",
      "LIN_TIM": 50,
      "COR_NAM": "대원고속(일반)"
    },
    {
      "TIM_TIM": "1050",
      "LIN_TIM": 50,
      "COR_NAM": "대원고속(일반)"
    },
    {
      "TIM_TIM": "1220",
      "LIN_TIM": 50,
      "COR_NAM": "대원고속(일반)"
    },
    {
      "TIM_TIM": "1305",
      "LIN_TIM": 50,
      "COR_NAM": "대원고속(일반)"
    },
    {
      "TIM_TIM": "1340",
      "LIN_TIM": 50,
      "COR_NAM": "대원고속(일반)"
    },
    {
      "TIM_TIM": "1420",
      "LIN_TIM": 50,
      "COR_NAM": "대원고속(일반)"
    },
    {
      "TIM_TIM": "1500",
      "LIN_TIM": 50,
      "COR_NAM": "대원고속(일반)"
    },
    {
      "TIM_TIM": "1620",
      "LIN_TIM": 50,
      "COR_NAM": "대원고속(일반)"
    },
    {
      "TIM_TIM": "1700",
      "LIN_TIM": 50,
      "COR_NAM": "대원고속(일반)"
    },
    {
      "TIM_TIM": "1740",
      "LIN_TIM": 50,
      "COR_NAM": "대원고속(일반)"
    },
    {
      "TIM_TIM": "1820",
      "LIN_TIM": 50,
      "COR_NAM": "대원고속(일반)"
    },
    {
      "TIM_TIM": "1900",
      "LIN_TIM": 50,
      "COR_NAM": "대원고속(일반)"
    },
    {
      "TIM_TIM": "2030",
      "LIN_TIM": 50,
      "COR_NAM": "대원고속(일반)"
    }
  ],
  "성남": [
    {
      "TIM_TIM": "0530",
      "LIN_TIM": 60,
      "COR_NAM": "대원고속(일반)"
    },
    {
      "TIM_TIM": "0610",
      "LIN_TIM": 60,
      "COR_NAM": "대원고속(일반)"
    },
    {
      "TIM_TIM": "0650",
      "LIN_TIM": 60,
      "COR_NAM": "대원고속(일반)"
    },
    {
      "TIM_TIM": "0730",
      "LIN_TIM": 60,
      "COR_NAM": "대원고속(일반)"
    },
    {
      "TIM_TIM": "0830",
      "LIN_TIM": 60,
      "COR_NAM": "대원고속(일반)"
    },
    {
      "TIM_TIM": "0900",
      "LIN_TIM": 60,
      "COR_NAM": "대원고속(일반)"
    },
    {
      "TIM_TIM": "0930",
      "LIN_TIM": 60,
      "COR_NAM": "대원고속(일반)"
    },
    {
      "TIM_TIM": "1010",
      "LIN_TIM": 60,
      "COR_NAM": "대원고속(일반)"
    },
    {
      "TIM_TIM": "1050",
      "LIN_TIM": 60,
      "COR_NAM": "대원고속(일반)"
    },
    {
      "TIM_TIM": "1220",
      "LIN_TIM": 60,
      "COR_NAM": "대원고속(일반)"
    },
    {
      "TIM_TIM": "1305",
      "LIN_TIM": 60,
      "COR_NAM": "대원고속(일반)"
    },
    {
      "TIM_TIM": "1340",
      "LIN_TIM": 60,
      "COR_NAM": "대원고속(일반)"
    },
    {
      "TIM_TIM": "1420",
      "LIN_TIM": 60,
      "COR_NAM": "대원고속(일반)"
    },
    {
      "TIM_TIM": "1500",
      "LIN_TIM": 60,
      "COR_NAM": "대원고속(일반)"
    },
    {
      "TIM_TIM": "1620",
      "LIN_TIM": 60,
      "COR_NAM": "대원고속(일반)"
    },
    {
      "TIM_TIM": "1700",
      "LIN_TIM": 60,
      "COR_NAM": "대원고속(일반)"
    },
    {
      "TIM_TIM": "1740",
      "LIN_TIM": 60,
      "COR_NAM": "대원고속(일반)"
    },
    {
      "TIM_TIM": "1820",
      "LIN_TIM": 60,
      "COR_NAM": "대원고속(일반)"
    },
    {
      "TIM_TIM": "1900",
      "LIN_TIM": 60,
      "COR_NAM": "대원고속(일반)"
    },
    {
      "TIM_TIM": "2030",
      "LIN_TIM": 60,
      "COR_NAM": "대원고속(일반)"
    }
  ],
  "함평": [
    {
      "TIM_TIM": "0830",
      "LIN_TIM": 235,
      "COR_NAM": "경기고속(우등)"
    },
    {
      "TIM_TIM": "1520",
      "LIN_TIM": 235,
      "COR_NAM": "금호고속(우등)"
    }
  ],
  "거창": [
    {
      "TIM_TIM": "0750",
      "LIN_TIM": 280,
      "COR_NAM": "거창고속(우등)"
    },
    {
      "TIM_TIM": "1200",
      "LIN_TIM": 280,
      "COR_NAM": "거창고속(우등)"
    },
    {
      "TIM_TIM": "1430",
      "LIN_TIM": 280,
      "COR_NAM": "거창고속(우등)"
    },
    {
      "TIM_TIM": "1620",
      "LIN_TIM": 280,
      "COR_NAM": "거창고속(우등)"
    }
  ],
  "세종청사": [
    {
      "TIM_TIM": "0640",
      "LIN_TIM": 133,
      "COR_NAM": "금남고속(우등)"
    },
    {
      "TIM_TIM": "0820",
      "LIN_TIM": 115,
      "COR_NAM": "금남고속(우등)"
    },
    {
      "TIM_TIM": "1040",
      "LIN_TIM": 115,
      "COR_NAM": "중부고속(우등)"
    },
    {
      "TIM_TIM": "1540",
      "LIN_TIM": 115,
      "COR_NAM": "금남고속(우등)"
    },
    {
      "TIM_TIM": "1830",
      "LIN_TIM": 115,
      "COR_NAM": "중부고속(우등)"
    },
    {
      "TIM_TIM": "1930",
      "LIN_TIM": 110,
      "COR_NAM": "삼흥고속(우등)"
    }
  ],
  "삼성": [
    {
      "TIM_TIM": "0710",
      "LIN_TIM": 120,
      "COR_NAM": "친선고속(일반)"
    },
    {
      "TIM_TIM": "1840",
      "LIN_TIM": 120,
      "COR_NAM": "친선고속(일반)"
    }
  ],
  "음성": [
    {
      "TIM_TIM": "0710",
      "LIN_TIM": 160,
      "COR_NAM": "친선고속(일반)"
    },
    {
      "TIM_TIM": "1110",
      "LIN_TIM": 140,
      "COR_NAM": "친선고속(일반)"
    },
    {
      "TIM_TIM": "1840",
      "LIN_TIM": 160,
      "COR_NAM": "친선고속(일반)"
    }
  ],
  "강릉": [
    {
      "TIM_TIM": "0630",
      "LIN_TIM": 210,
      "COR_NAM": "강원여객(우등)"
    },
    {
      "TIM_TIM": "0810",
      "LIN_TIM": 210,
      "COR_NAM": "대원고속(우등)"
    },
    {
      "TIM_TIM": "0930",
      "LIN_TIM": 210,
      "COR_NAM": "경기고속(우등)"
    },
    {
      "TIM_TIM": "1120",
      "LIN_TIM": 210,
      "COR_NAM": "동해상사고속(우등)"
    },
    {
      "TIM_TIM": "1240",
      "LIN_TIM": 210,
      "COR_NAM": "강원여객(우등)"
    },
    {
      "TIM_TIM": "1400",
      "LIN_TIM": 210,
      "COR_NAM": "대원고속(우등)"
    },
    {
      "TIM_TIM": "1540",
      "LIN_TIM": 210,
      "COR_NAM": "강원여객(우등)"
    },
    {
      "TIM_TIM": "1720",
      "LIN_TIM": 210,
      "COR_NAM": "대원고속(우등)"
    },
    {
      "TIM_TIM": "1850",
      "LIN_TIM": 210,
      "COR_NAM": "경기고속(우등)"
    }
  ],
  "예산": [
    {
      "TIM_TIM": "0755",
      "LIN_TIM": 110,
      "COR_NAM": "충남고속(일반)"
    },
    {
      "TIM_TIM": "0830",
      "LIN_TIM": 110,
      "COR_NAM": "충남고속(우등)"
    },
    {
      "TIM_TIM": "1350",
      "LIN_TIM": 90,
      "COR_NAM": "충남고속(우등)"
    },
    {
      "TIM_TIM": "1640",
      "LIN_TIM": 110,
      "COR_NAM": "충남고속(일반)"
    },
    {
      "TIM_TIM": "1840",
      "LIN_TIM": 110,
      "COR_NAM": "충남고속(우등)"
    }
  ],
  "임성동": [
    {
      "TIM_TIM": "0830",
      "LIN_TIM": 118,
      "COR_NAM": "충남고속(우등)"
    },
    {
      "TIM_TIM": "1840",
      "LIN_TIM": 118,
      "COR_NAM": "충남고속(우등)"
    }
  ],
  "이월": [
    {
      "TIM_TIM": "0600",
      "LIN_TIM": 207,
      "COR_NAM": "대원고속(일반)"
    },
    {
      "TIM_TIM": "1200",
      "LIN_TIM": 207,
      "COR_NAM": "경일여객(일반)"
    },
    {
      "TIM_TIM": "1420",
      "LIN_TIM": 207,
      "COR_NAM": "친선고속(일반)"
    },
    {
      "TIM_TIM": "1600",
      "LIN_TIM": 207,
      "COR_NAM": "대원고속(일반)"
    }
  ],
  "괴산": [
    {
      "TIM_TIM": "0805",
      "LIN_TIM": 170,
      "COR_NAM": "친선고속(일반)"
    },
    {
      "TIM_TIM": "1220",
      "LIN_TIM": 170,
      "COR_NAM": "친선고속(일반)"
    },
    {
      "TIM_TIM": "1730",
      "LIN_TIM": 170,
      "COR_NAM": "친선고속(일반)"
    }
  ],
  "청주북부터미널": [
    {
      "TIM_TIM": "0725",
      "LIN_TIM": 100,
      "COR_NAM": "금남고속(일반)"
    },
    {
      "TIM_TIM": "1035",
      "LIN_TIM": 100,
      "COR_NAM": "서울고속(우등)"
    },
    {
      "TIM_TIM": "1340",
      "LIN_TIM": 100,
      "COR_NAM": "금남고속(일반)"
    },
    {
      "TIM_TIM": "1600",
      "LIN_TIM": 100,
      "COR_NAM": "친선고속(일반)"
    },
    {
      "TIM_TIM": "1755",
      "LIN_TIM": 100,
      "COR_NAM": "서울고속(우등)"
    },
    {
      "TIM_TIM": "2000",
      "LIN_TIM": 100,
      "COR_NAM": "금남고속(일반)"
    }
  ],
  "영해": [
    {
      "TIM_TIM": "1140",
      "LIN_TIM": 440,
      "COR_NAM": "아성고속(우등)"
    }
  ],
  "강구": [
    {
      "TIM_TIM": "1140",
      "LIN_TIM": 406,
      "COR_NAM": "아성고속(우등)"
    }
  ],
  "경북도청": [
    {
      "TIM_TIM": "0640",
      "LIN_TIM": 250,
      "COR_NAM": "경북고속(우등)"
    },
    {
      "TIM_TIM": "1230",
      "LIN_TIM": 250,
      "COR_NAM": "경북고속(우등)"
    }
  ],
  "문막": [
    {
      "TIM_TIM": "0615",
      "LIN_TIM": 120,
      "COR_NAM": "경기고속(우등)"
    },
    {
      "TIM_TIM": "0640",
      "LIN_TIM": 120,
      "COR_NAM": "경기고속(우등)"
    },
    {
      "TIM_TIM": "0840",
      "LIN_TIM": 120,
      "COR_NAM": "경기고속(우등)"
    },
    {
      "TIM_TIM": "0940",
      "LIN_TIM": 120,
      "COR_NAM": "경기고속(우등)"
    },
    {
      "TIM_TIM": "1030",
      "LIN_TIM": 120,
      "COR_NAM": "경기고속(우등)"
    },
    {
      "TIM_TIM": "1120",
      "LIN_TIM": 120,
      "COR_NAM": "경기고속(우등)"
    },
    {
      "TIM_TIM": "1235",
      "LIN_TIM": 120,
      "COR_NAM": "경기고속(우등)"
    },
    {
      "TIM_TIM": "1310",
      "LIN_TIM": 120,
      "COR_NAM": "경기고속(우등)"
    },
    {
      "TIM_TIM": "1440",
      "LIN_TIM": 120,
      "COR_NAM": "경기고속(우등)"
    },
    {
      "TIM_TIM": "1540",
      "LIN_TIM": 120,
      "COR_NAM": "경기고속(우등)"
    },
    {
      "TIM_TIM": "1640",
      "LIN_TIM": 120,
      "COR_NAM": "경기고속(우등)"
    },
    {
      "TIM_TIM": "1740",
      "LIN_TIM": 120,
      "COR_NAM": "경기고속(우등)"
    },
    {
      "TIM_TIM": "1940",
      "LIN_TIM": 120,
      "COR_NAM": "경기고속(우등)"
    }
  ],
  "장지역": [
    {
      "TIM_TIM": "0540",
      "LIN_TIM": 50,
      "COR_NAM": "경기고속(일반)"
    },
    {
      "TIM_TIM": "0610",
      "LIN_TIM": 50,
      "COR_NAM": "경기고속(일반)"
    },
    {
      "TIM_TIM": "0635",
      "LIN_TIM": 50,
      "COR_NAM": "경기고속(일반)"
    },
    {
      "TIM_TIM": "0710",
      "LIN_TIM": 50,
      "COR_NAM": "경기고속(일반)"
    },
    {
      "TIM_TIM": "0740",
      "LIN_TIM": 50,
      "COR_NAM": "경기고속(일반)"
    },
    {
      "TIM_TIM": "0810",
      "LIN_TIM": 50,
      "COR_NAM": "경기고속(일반)"
    },
    {
      "TIM_TIM": "0850",
      "LIN_TIM": 50,
      "COR_NAM": "경기고속(일반)"
    },
    {
      "TIM_TIM": "0930",
      "LIN_TIM": 50,
      "COR_NAM": "경기고속(일반)"
    },
    {
      "TIM_TIM": "1030",
      "LIN_TIM": 50,
      "COR_NAM": "경기고속(일반)"
    },
    {
      "TIM_TIM": "1110",
      "LIN_TIM": 50,
      "COR_NAM": "경기고속(일반)"
    },
    {
      "TIM_TIM": "1200",
      "LIN_TIM": 50,
      "COR_NAM": "경기고속(일반)"
    },
    {
      "TIM_TIM": "1240",
      "LIN_TIM": 50,
      "COR_NAM": "경기고속(일반)"
    },
    {
      "TIM_TIM": "1310",
      "LIN_TIM": 50,
      "COR_NAM": "경기고속(일반)"
    },
    {
      "TIM_TIM": "1340",
      "LIN_TIM": 50,
      "COR_NAM": "경기고속(일반)"
    },
    {
      "TIM_TIM": "1440",
      "LIN_TIM": 50,
      "COR_NAM": "경기고속(일반)"
    },
    {
      "TIM_TIM": "1510",
      "LIN_TIM": 50,
      "COR_NAM": "경기고속(일반)"
    },
    {
      "TIM_TIM": "1550",
      "LIN_TIM": 50,
      "COR_NAM": "경기고속(일반)"
    },
    {
      "TIM_TIM": "1630",
      "LIN_TIM": 50,
      "COR_NAM": "경기고속(일반)"
    },
    {
      "TIM_TIM": "1730",
      "LIN_TIM": 50,
      "COR_NAM": "경기고속(일반)"
    },
    {
      "TIM_TIM": "1820",
      "LIN_TIM": 50,
      "COR_NAM": "경기고속(일반)"
    },
    {
      "TIM_TIM": "1900",
      "LIN_TIM": 50,
      "COR_NAM": "경기고속(일반)"
    }
  ],
  "이천": [
    {
      "TIM_TIM": "0630",
      "LIN_TIM": 90,
      "COR_NAM": "대원고속(일반)"
    },
    {
      "TIM_TIM": "0710",
      "LIN_TIM": 90,
      "COR_NAM": "경기고속(일반)"
    },
    {
      "TIM_TIM": "0735",
      "LIN_TIM": 90,
      "COR_NAM": "대원고속(일반)"
    },
    {
      "TIM_TIM": "1150",
      "LIN_TIM": 90,
      "COR_NAM": "경기고속(일반)"
    },
    {
      "TIM_TIM": "1250",
      "LIN_TIM": 90,
      "COR_NAM": "대원고속(일반)"
    },
    {
      "TIM_TIM": "1500",
      "LIN_TIM": 90,
      "COR_NAM": "대원고속(일반)"
    },
    {
      "TIM_TIM": "1700",
      "LIN_TIM": 90,
      "COR_NAM": "경기고속(일반)"
    }
  ],
  "중앙대(안성)": [
    {
      "TIM_TIM": "0630",
      "LIN_TIM": 75,
      "COR_NAM": "대원고속(일반)"
    },
    {
      "TIM_TIM": "0800",
      "LIN_TIM": 75,
      "COR_NAM": "대원고속(일반)"
    },
    {
      "TIM_TIM": "1035",
      "LIN_TIM": 75,
      "COR_NAM": "대원고속(일반)"
    },
    {
      "TIM_TIM": "1300",
      "LIN_TIM": 94,
      "COR_NAM": "대원고속(일반)"
    },
    {
      "TIM_TIM": "1400",
      "LIN_TIM": 94,
      "COR_NAM": "대원고속(일반)"
    },
    {
      "TIM_TIM": "1620",
      "LIN_TIM": 94,
      "COR_NAM": "대원고속(일반)"
    },
    {
      "TIM_TIM": "1910",
      "LIN_TIM": 75,
      "COR_NAM": "대원고속(일반)"
    }
  ],
  "대림동산": [
    {
      "TIM_TIM": "0630",
      "LIN_TIM": 70,
      "COR_NAM": "대원고속(일반)"
    },
    {
      "TIM_TIM": "0800",
      "LIN_TIM": 70,
      "COR_NAM": "대원고속(일반)"
    },
    {
      "TIM_TIM": "1035",
      "LIN_TIM": 70,
      "COR_NAM": "대원고속(일반)"
    },
    {
      "TIM_TIM": "1300",
      "LIN_TIM": 88,
      "COR_NAM": "대원고속(일반)"
    },
    {
      "TIM_TIM": "1400",
      "LIN_TIM": 88,
      "COR_NAM": "대원고속(일반)"
    },
    {
      "TIM_TIM": "1620",
      "LIN_TIM": 88,
      "COR_NAM": "대원고속(일반)"
    },
    {
      "TIM_TIM": "1910",
      "LIN_TIM": 70,
      "COR_NAM": "대원고속(일반)"
    }
  ],
  "공도": [
    {
      "TIM_TIM": "0630",
      "LIN_TIM": 65,
      "COR_NAM": "대원고속(일반)"
    },
    {
      "TIM_TIM": "0800",
      "LIN_TIM": 65,
      "COR_NAM": "대원고속(일반)"
    },
    {
      "TIM_TIM": "1035",
      "LIN_TIM": 65,
      "COR_NAM": "대원고속(일반)"
    },
    {
      "TIM_TIM": "1300",
      "LIN_TIM": 78,
      "COR_NAM": "대원고속(일반)"
    },
    {
      "TIM_TIM": "1400",
      "LIN_TIM": 78,
      "COR_NAM": "대원고속(일반)"
    },
    {
      "TIM_TIM": "1620",
      "LIN_TIM": 78,
      "COR_NAM": "대원고속(일반)"
    },
    {
      "TIM_TIM": "1910",
      "LIN_TIM": 65,
      "COR_NAM": "대원고속(일반)"
    }
  ],
  "수원": [
    {
      "TIM_TIM": "0600",
      "LIN_TIM": 92,
      "COR_NAM": "대원고속(일반)"
    },
    {
      "TIM_TIM": "0650",
      "LIN_TIM": 80,
      "COR_NAM": "경북고속(우등)"
    },
    {
      "TIM_TIM": "0750",
      "LIN_TIM": 80,
      "COR_NAM": "거창고속(우등)"
    },
    {
      "TIM_TIM": "0850",
      "LIN_TIM": 75,
      "COR_NAM": "경북고속(우등)"
    },
    {
      "TIM_TIM": "1100",
      "LIN_TIM": 80,
      "COR_NAM": "경북고속(우등)"
    },
    {
      "TIM_TIM": "1200",
      "LIN_TIM": 80,
      "COR_NAM": "거창고속(우등)"
    },
    {
      "TIM_TIM": "1200",
      "LIN_TIM": 92,
      "COR_NAM": "경일여객(일반)"
    },
    {
      "TIM_TIM": "1330",
      "LIN_TIM": 80,
      "COR_NAM": "경북고속(우등)"
    },
    {
      "TIM_TIM": "1420",
      "LIN_TIM": 92,
      "COR_NAM": "친선고속(일반)"
    },
    {
      "TIM_TIM": "1430",
      "LIN_TIM": 80,
      "COR_NAM": "거창고속(우등)"
    },
    {
      "TIM_TIM": "1600",
      "LIN_TIM": 92,
      "COR_NAM": "대원고속(일반)"
    },
    {
      "TIM_TIM": "1610",
      "LIN_TIM": 75,
      "COR_NAM": "경북고속(우등)"
    },
    {
      "TIM_TIM": "1620",
      "LIN_TIM": 80,
      "COR_NAM": "거창고속(우등)"
    }
  ],
  "부안": [
    {
      "TIM_TIM": "1520",
      "LIN_TIM": 210,
      "COR_NAM": "호남고속(우등)"
    }
  ],
  "서산": [
    {
      "TIM_TIM": "1050",
      "LIN_TIM": 109,
      "COR_NAM": "한양고속(우등)"
    },
    {
      "TIM_TIM": "1530",
      "LIN_TIM": 109,
      "COR_NAM": "충남고속(우등)"
    },
    {
      "TIM_TIM": "1645",
      "LIN_TIM": 109,
      "COR_NAM": "한양고속(우등)"
    },
    {
      "TIM_TIM": "2010",
      "LIN_TIM": 109,
      "COR_NAM": "충남고속(우등)"
    }
  ],
  "충주": [
    {
      "TIM_TIM": "0650",
      "LIN_TIM": 140,
      "COR_NAM": "대원고속(우등)"
    },
    {
      "TIM_TIM": "1010",
      "LIN_TIM": 140,
      "COR_NAM": "대원고속(일반)"
    },
    {
      "TIM_TIM": "1340",
      "LIN_TIM": 140,
      "COR_NAM": "대원고속(우등)"
    },
    {
      "TIM_TIM": "1710",
      "LIN_TIM": 140,
      "COR_NAM": "대원고속(일반)"
    }
  ],
  "감곡": [
    {
      "TIM_TIM": "0805",
      "LIN_TIM": 110,
      "COR_NAM": "친선고속(일반)"
    },
    {
      "TIM_TIM": "1220",
      "LIN_TIM": 110,
      "COR_NAM": "친선고속(일반)"
    },
    {
      "TIM_TIM": "1730",
      "LIN_TIM": 110,
      "COR_NAM": "친선고속(일반)"
    }
  ],
  "무극": [
    {
      "TIM_TIM": "0710",
      "LIN_TIM": 130,
      "COR_NAM": "친선고속(일반)"
    },
    {
      "TIM_TIM": "1110",
      "LIN_TIM": 125,
      "COR_NAM": "친선고속(일반)"
    },
    {
      "TIM_TIM": "1840",
      "LIN_TIM": 130,
      "COR_NAM": "친선고속(일반)"
    }
  ],
  "공주": [
    {
      "TIM_TIM": "0640",
      "LIN_TIM": 170,
      "COR_NAM": "금남고속(우등)"
    },
    {
      "TIM_TIM": "0940",
      "LIN_TIM": 110,
      "COR_NAM": "대원고속(우등)"
    },
    {
      "TIM_TIM": "1120",
      "LIN_TIM": 122,
      "COR_NAM": "금남고속(우등)"
    },
    {
      "TIM_TIM": "1300",
      "LIN_TIM": 110,
      "COR_NAM": "삼흥고속(우등)"
    },
    {
      "TIM_TIM": "1440",
      "LIN_TIM": 122,
      "COR_NAM": "금남고속(우등)"
    },
    {
      "TIM_TIM": "1620",
      "LIN_TIM": 110,
      "COR_NAM": "대원고속(우등)"
    },
    {
      "TIM_TIM": "1800",
      "LIN_TIM": 122,
      "COR_NAM": "금남고속(우등)"
    },
    {
      "TIM_TIM": "1930",
      "LIN_TIM": 160,
      "COR_NAM": "삼흥고속(우등)"
    }
  ],
  "부여": [
    {
      "TIM_TIM": "0640",
      "LIN_TIM": 208,
      "COR_NAM": "금남고속(우등)"
    },
    {
      "TIM_TIM": "1120",
      "LIN_TIM": 160,
      "COR_NAM": "금남고속(우등)"
    },
    {
      "TIM_TIM": "1350",
      "LIN_TIM": 165,
      "COR_NAM": "충남고속(우등)"
    },
    {
      "TIM_TIM": "1440",
      "LIN_TIM": 160,
      "COR_NAM": "금남고속(우등)"
    },
    {
      "TIM_TIM": "1800",
      "LIN_TIM": 160,
      "COR_NAM": "금남고속(우등)"
    }
  ],
  "청양": [
    {
      "TIM_TIM": "0830",
      "LIN_TIM": 170,
      "COR_NAM": "충남고속(우등)"
    },
    {
      "TIM_TIM": "1350",
      "LIN_TIM": 130,
      "COR_NAM": "충남고속(우등)"
    },
    {
      "TIM_TIM": "1840",
      "LIN_TIM": 170,
      "COR_NAM": "충남고속(우등)"
    }
  ],
  "울산": [
    {
      "TIM_TIM": "0930",
      "LIN_TIM": 335,
      "COR_NAM": "아성고속(우등)"
    },
    {
      "TIM_TIM": "1310",
      "LIN_TIM": 335,
      "COR_NAM": "천마고속(우등)"
    },
    {
      "TIM_TIM": "1450",
      "LIN_TIM": 335,
      "COR_NAM": "경기고속(우등)"
    },
    {
      "TIM_TIM": "1640",
      "LIN_TIM": 335,
      "COR_NAM": "아성고속(우등)"
    },
    {
      "TIM_TIM": "2359",
      "LIN_TIM": 335,
      "COR_NAM": "아성고속(심야우등)"
    }
  ],
  "삽교천": [
    {
      "TIM_TIM": "0730",
      "LIN_TIM": 70,
      "COR_NAM": "한양고속(우등)"
    },
    {
      "TIM_TIM": "1150",
      "LIN_TIM": 70,
      "COR_NAM": "충남고속(우등)"
    },
    {
      "TIM_TIM": "1700",
      "LIN_TIM": 70,
      "COR_NAM": "충남고속(일반)"
    },
    {
      "TIM_TIM": "1955",
      "LIN_TIM": 70,
      "COR_NAM": "한양고속(우등)"
    }
  ],
  "고한사북공영": [
    {
      "TIM_TIM": "0610",
      "LIN_TIM": 200,
      "COR_NAM": "경기고속(프리미엄)"
    },
    {
      "TIM_TIM": "1130",
      "LIN_TIM": 200,
      "COR_NAM": "경기고속(프리미엄)"
    },
    {
      "TIM_TIM": "1520",
      "LIN_TIM": 200,
      "COR_NAM": "경기고속(우등)"
    },
    {
      "TIM_TIM": "1750",
      "LIN_TIM": 200,
      "COR_NAM": "경기고속(프리미엄)"
    }
  ],
  "죽산": [
    {
      "TIM_TIM": "0600",
      "LIN_TIM": 182,
      "COR_NAM": "대원고속(일반)"
    },
    {
      "TIM_TIM": "1200",
      "LIN_TIM": 182,
      "COR_NAM": "경일여객(일반)"
    },
    {
      "TIM_TIM": "1420",
      "LIN_TIM": 182,
      "COR_NAM": "친선고속(일반)"
    },
    {
      "TIM_TIM": "1600",
      "LIN_TIM": 182,
      "COR_NAM": "대원고속(일반)"
    }
  ],
  "두원공대": [
    {
      "TIM_TIM": "0600",
      "LIN_TIM": 187,
      "COR_NAM": "대원고속(일반)"
    },
    {
      "TIM_TIM": "1200",
      "LIN_TIM": 187,
      "COR_NAM": "경일여객(일반)"
    },
    {
      "TIM_TIM": "1420",
      "LIN_TIM": 187,
      "COR_NAM": "친선고속(일반)"
    },
    {
      "TIM_TIM": "1600",
      "LIN_TIM": 187,
      "COR_NAM": "대원고속(일반)"
    }
  ],
  "일죽": [
    {
      "TIM_TIM": "0710",
      "LIN_TIM": 110,
      "COR_NAM": "친선고속(일반)"
    },
    {
      "TIM_TIM": "1840",
      "LIN_TIM": 110,
      "COR_NAM": "친선고속(일반)"
    }
  ],
  "한경대": [
    {
      "TIM_TIM": "0630",
      "LIN_TIM": 80,
      "COR_NAM": "대원고속(일반)"
    },
    {
      "TIM_TIM": "0800",
      "LIN_TIM": 80,
      "COR_NAM": "대원고속(일반)"
    },
    {
      "TIM_TIM": "1035",
      "LIN_TIM": 80,
      "COR_NAM": "대원고속(일반)"
    },
    {
      "TIM_TIM": "1910",
      "LIN_TIM": 80,
      "COR_NAM": "대원고속(일반)"
    }
  ],
  "안산": [
    {
      "TIM_TIM": "0600",
      "LIN_TIM": 50,
      "COR_NAM": "대원고속(일반)"
    },
    {
      "TIM_TIM": "0640",
      "LIN_TIM": 40,
      "COR_NAM": "경북고속(우등)"
    },
    {
      "TIM_TIM": "0650",
      "LIN_TIM": 40,
      "COR_NAM": "경북고속(우등)"
    },
    {
      "TIM_TIM": "0710",
      "LIN_TIM": 40,
      "COR_NAM": "친선고속(일반)"
    },
    {
      "TIM_TIM": "0730",
      "LIN_TIM": 40,
      "COR_NAM": "대원고속(우등)"
    },
    {
      "TIM_TIM": "0745",
      "LIN_TIM": 40,
      "COR_NAM": "경북고속(우등)"
    },
    {
      "TIM_TIM": "0750",
      "LIN_TIM": 40,
      "COR_NAM": "거창고속(우등)"
    },
    {
      "TIM_TIM": "0850",
      "LIN_TIM": 35,
      "COR_NAM": "경북고속(우등)"
    },
    {
      "TIM_TIM": "0900",
      "LIN_TIM": 40,
      "COR_NAM": "경북고속(우등)"
    },
    {
      "TIM_TIM": "1100",
      "LIN_TIM": 40,
      "COR_NAM": "경북고속(우등)"
    },
    {
      "TIM_TIM": "1110",
      "LIN_TIM": 40,
      "COR_NAM": "친선고속(일반)"
    },
    {
      "TIM_TIM": "1120",
      "LIN_TIM": 40,
      "COR_NAM": "경북고속(우등)"
    },
    {
      "TIM_TIM": "1200",
      "LIN_TIM": 40,
      "COR_NAM": "거창고속(우등)"
    },
    {
      "TIM_TIM": "1200",
      "LIN_TIM": 50,
      "COR_NAM": "경일여객(일반)"
    },
    {
      "TIM_TIM": "1230",
      "LIN_TIM": 40,
      "COR_NAM": "경북고속(우등)"
    },
    {
      "TIM_TIM": "1325",
      "LIN_TIM": 40,
      "COR_NAM": "대원고속(우등)"
    },
    {
      "TIM_TIM": "1330",
      "LIN_TIM": 40,
      "COR_NAM": "경북고속(우등)"
    },
    {
      "TIM_TIM": "1420",
      "LIN_TIM": 50,
      "COR_NAM": "친선고속(일반)"
    },
    {
      "TIM_TIM": "1430",
      "LIN_TIM": 40,
      "COR_NAM": "거창고속(우등)"
    },
    {
      "TIM_TIM": "1455",
      "LIN_TIM": 40,
      "COR_NAM": "경북고속(우등)"
    },
    {
      "TIM_TIM": "1510",
      "LIN_TIM": 40,
      "COR_NAM": "대원고속(우등)"
    },
    {
      "TIM_TIM": "1600",
      "LIN_TIM": 50,
      "COR_NAM": "대원고속(일반)"
    },
    {
      "TIM_TIM": "1610",
      "LIN_TIM": 35,
      "COR_NAM": "경북고속(우등)"
    },
    {
      "TIM_TIM": "1620",
      "LIN_TIM": 40,
      "COR_NAM": "거창고속(우등)"
    },
    {
      "TIM_TIM": "1710",
      "LIN_TIM": 40,
      "COR_NAM": "경북고속(우등)"
    },
    {
      "TIM_TIM": "1715",
      "LIN_TIM": 40,
      "COR_NAM": "대원고속(우등)"
    },
    {
      "TIM_TIM": "1830",
      "LIN_TIM": 40,
      "COR_NAM": "경북고속(우등)"
    },
    {
      "TIM_TIM": "1840",
      "LIN_TIM": 40,
      "COR_NAM": "친선고속(일반)"
    },
    {
      "TIM_TIM": "1930",
      "LIN_TIM": 40,
      "COR_NAM": "경북고속(우등)"
    }
  ],
  "거제(고현)": [
    {
      "TIM_TIM": "0720",
      "LIN_TIM": 330,
      "COR_NAM": "진안고속(우등)"
    },
    {
      "TIM_TIM": "1050",
      "LIN_TIM": 330,
      "COR_NAM": "진안고속(우등)"
    },
    {
      "TIM_TIM": "1220",
      "LIN_TIM": 330,
      "COR_NAM": "진안고속(우등)"
    },
    {
      "TIM_TIM": "1730",
      "LIN_TIM": 330,
      "COR_NAM": "진안고속(우등)"
    }
  ],
  "기지시": [
    {
      "TIM_TIM": "0640",
      "LIN_TIM": 71,
      "COR_NAM": "충남고속(우등)"
    },
    {
      "TIM_TIM": "0730",
      "LIN_TIM": 88,
      "COR_NAM": "한양고속(우등)"
    },
    {
      "TIM_TIM": "0820",
      "LIN_TIM": 71,
      "COR_NAM": "충남고속(우등)"
    },
    {
      "TIM_TIM": "0910",
      "LIN_TIM": 71,
      "COR_NAM": "한양고속(우등)"
    },
    {
      "TIM_TIM": "1000",
      "LIN_TIM": 71,
      "COR_NAM": "충남고속(우등)"
    },
    {
      "TIM_TIM": "1055",
      "LIN_TIM": 71,
      "COR_NAM": "한양고속(우등)"
    },
    {
      "TIM_TIM": "1150",
      "LIN_TIM": 88,
      "COR_NAM": "충남고속(우등)"
    },
    {
      "TIM_TIM": "1240",
      "LIN_TIM": 71,
      "COR_NAM": "한양고속(우등)"
    },
    {
      "TIM_TIM": "1330",
      "LIN_TIM": 71,
      "COR_NAM": "충남고속(우등)"
    },
    {
      "TIM_TIM": "1420",
      "LIN_TIM": 71,
      "COR_NAM": "한양고속(우등)"
    },
    {
      "TIM_TIM": "1515",
      "LIN_TIM": 71,
      "COR_NAM": "충남고속(우등)"
    },
    {
      "TIM_TIM": "1610",
      "LIN_TIM": 71,
      "COR_NAM": "한양고속(우등)"
    },
    {
      "TIM_TIM": "1700",
      "LIN_TIM": 88,
      "COR_NAM": "충남고속(일반)"
    },
    {
      "TIM_TIM": "1750",
      "LIN_TIM": 71,
      "COR_NAM": "한양고속(우등)"
    },
    {
      "TIM_TIM": "1850",
      "LIN_TIM": 71,
      "COR_NAM": "충남고속(우등)"
    },
    {
      "TIM_TIM": "1955",
      "LIN_TIM": 88,
      "COR_NAM": "한양고속(우등)"
    },
    {
      "TIM_TIM": "2100",
      "LIN_TIM": 71,
      "COR_NAM": "충남고속(우등)"
    }
  ],
  "대소": [
    {
      "TIM_TIM": "0710",
      "LIN_TIM": 125,
      "COR_NAM": "친선고속(일반)"
    },
    {
      "TIM_TIM": "1110",
      "LIN_TIM": 110,
      "COR_NAM": "친선고속(일반)"
    },
    {
      "TIM_TIM": "1840",
      "LIN_TIM": 125,
      "COR_NAM": "친선고속(일반)"
    }
  ],
  "신례원": [
    {
      "TIM_TIM": "0755",
      "LIN_TIM": 101,
      "COR_NAM": "충남고속(일반)"
    },
    {
      "TIM_TIM": "0830",
      "LIN_TIM": 101,
      "COR_NAM": "충남고속(우등)"
    },
    {
      "TIM_TIM": "1350",
      "LIN_TIM": 80,
      "COR_NAM": "충남고속(우등)"
    },
    {
      "TIM_TIM": "1640",
      "LIN_TIM": 101,
      "COR_NAM": "충남고속(일반)"
    },
    {
      "TIM_TIM": "1840",
      "LIN_TIM": 101,
      "COR_NAM": "충남고속(우등)"
    }
  ],
  "운곡": [
    {
      "TIM_TIM": "0830",
      "LIN_TIM": 158,
      "COR_NAM": "충남고속(우등)"
    },
    {
      "TIM_TIM": "1350",
      "LIN_TIM": 120,
      "COR_NAM": "충남고속(우등)"
    },
    {
      "TIM_TIM": "1840",
      "LIN_TIM": 158,
      "COR_NAM": "충남고속(우등)"
    }
  ],
  "원주": [
    {
      "TIM_TIM": "0615",
      "LIN_TIM": 140,
      "COR_NAM": "경기고속(우등)"
    },
    {
      "TIM_TIM": "0640",
      "LIN_TIM": 140,
      "COR_NAM": "경기고속(우등)"
    },
    {
      "TIM_TIM": "0840",
      "LIN_TIM": 140,
      "COR_NAM": "경기고속(우등)"
    },
    {
      "TIM_TIM": "0940",
      "LIN_TIM": 140,
      "COR_NAM": "경기고속(우등)"
    },
    {
      "TIM_TIM": "1030",
      "LIN_TIM": 140,
      "COR_NAM": "경기고속(우등)"
    },
    {
      "TIM_TIM": "1120",
      "LIN_TIM": 140,
      "COR_NAM": "경기고속(우등)"
    },
    {
      "TIM_TIM": "1235",
      "LIN_TIM": 140,
      "COR_NAM": "경기고속(우등)"
    },
    {
      "TIM_TIM": "1310",
      "LIN_TIM": 140,
      "COR_NAM": "경기고속(우등)"
    },
    {
      "TIM_TIM": "1440",
      "LIN_TIM": 140,
      "COR_NAM": "경기고속(우등)"
    },
    {
      "TIM_TIM": "1540",
      "LIN_TIM": 140,
      "COR_NAM": "경기고속(우등)"
    },
    {
      "TIM_TIM": "1640",
      "LIN_TIM": 140,
      "COR_NAM": "경기고속(우등)"
    },
    {
      "TIM_TIM": "1740",
      "LIN_TIM": 140,
      "COR_NAM": "경기고속(우등)"
    },
    {
      "TIM_TIM": "1940",
      "LIN_TIM": 140,
      "COR_NAM": "경기고속(우등)"
    }
  ],
  "경주": [
    {
      "TIM_TIM": "1000",
      "LIN_TIM": 275,
      "COR_NAM": "아성고속(우등)"
    },
    {
      "TIM_TIM": "1140",
      "LIN_TIM": 300,
      "COR_NAM": "아성고속(우등)"
    },
    {
      "TIM_TIM": "1400",
      "LIN_TIM": 275,
      "COR_NAM": "아성고속(우등)"
    },
    {
      "TIM_TIM": "1600",
      "LIN_TIM": 275,
      "COR_NAM": "천마고속(우등)"
    },
    {
      "TIM_TIM": "1810",
      "LIN_TIM": 275,
      "COR_NAM": "경기고속(우등)"
    },
    {
      "TIM_TIM": "2359",
      "LIN_TIM": 295,
      "COR_NAM": "천마고속(심야우등)"
    }
  ],
  "청주대정류소": [
    {
      "TIM_TIM": "0725",
      "LIN_TIM": 120,
      "COR_NAM": "금남고속(일반)"
    },
    {
      "TIM_TIM": "1035",
      "LIN_TIM": 120,
      "COR_NAM": "서울고속(우등)"
    },
    {
      "TIM_TIM": "1340",
      "LIN_TIM": 120,
      "COR_NAM": "금남고속(일반)"
    },
    {
      "TIM_TIM": "1600",
      "LIN_TIM": 120,
      "COR_NAM": "친선고속(일반)"
    },
    {
      "TIM_TIM": "1755",
      "LIN_TIM": 120,
      "COR_NAM": "서울고속(우등)"
    },
    {
      "TIM_TIM": "2000",
      "LIN_TIM": 120,
      "COR_NAM": "금남고속(일반)"
    }
  ],
  "유성": [
    {
      "TIM_TIM": "0610",
      "LIN_TIM": 154,
      "COR_NAM": "금남고속(우등)"
    },
    {
      "TIM_TIM": "0710",
      "LIN_TIM": 154,
      "COR_NAM": "금남고속(일반)"
    },
    {
      "TIM_TIM": "0940",
      "LIN_TIM": 154,
      "COR_NAM": "금남고속(우등)"
    },
    {
      "TIM_TIM": "1120",
      "LIN_TIM": 154,
      "COR_NAM": "금남고속(우등)"
    },
    {
      "TIM_TIM": "1300",
      "LIN_TIM": 154,
      "COR_NAM": "금남고속(우등)"
    },
    {
      "TIM_TIM": "1440",
      "LIN_TIM": 154,
      "COR_NAM": "금남고속(우등)"
    },
    {
      "TIM_TIM": "1615",
      "LIN_TIM": 154,
      "COR_NAM": "금남고속(우등)"
    },
    {
      "TIM_TIM": "1710",
      "LIN_TIM": 154,
      "COR_NAM": "금남고속(우등)"
    },
    {
      "TIM_TIM": "1850",
      "LIN_TIM": 154,
      "COR_NAM": "금남고속(우등)"
    },
    {
      "TIM_TIM": "2030",
      "LIN_TIM": 154,
      "COR_NAM": "금남고속(우등)"
    }
  ],
  "도리원": [
    {
      "TIM_TIM": "0850",
      "LIN_TIM": 312,
      "COR_NAM": "경북고속(우등)"
    },
    {
      "TIM_TIM": "1610",
      "LIN_TIM": 312,
      "COR_NAM": "경북고속(우등)"
    }
  ],
  "후포": [
    {
      "TIM_TIM": "1140",
      "LIN_TIM": 463,
      "COR_NAM": "아성고속(우등)"
    }
  ],
  "영덕": [
    {
      "TIM_TIM": "1140",
      "LIN_TIM": 417,
      "COR_NAM": "아성고속(우등)"
    }
  ],
  "명지대": [
    {
      "TIM_TIM": "0745",
      "LIN_TIM": 100,
      "COR_NAM": "경남여객(일반)"
    },
    {
      "TIM_TIM": "1005",
      "LIN_TIM": 100,
      "COR_NAM": "경남여객(일반)"
    },
    {
      "TIM_TIM": "1300",
      "LIN_TIM": 100,
      "COR_NAM": "경남여객(일반)"
    },
    {
      "TIM_TIM": "1530",
      "LIN_TIM": 100,
      "COR_NAM": "경남여객(일반)"
    },
    {
      "TIM_TIM": "1820",
      "LIN_TIM": 100,
      "COR_NAM": "경남여객(일반)"
    },
    {
      "TIM_TIM": "2105",
      "LIN_TIM": 106,
      "COR_NAM": "경남여객(일반)"
    }
  ],
  "덕평IC": [
    {
      "TIM_TIM": "0630",
      "LIN_TIM": 75,
      "COR_NAM": "대원고속(일반)"
    },
    {
      "TIM_TIM": "0710",
      "LIN_TIM": 75,
      "COR_NAM": "경기고속(일반)"
    },
    {
      "TIM_TIM": "0735",
      "LIN_TIM": 75,
      "COR_NAM": "대원고속(일반)"
    },
    {
      "TIM_TIM": "1150",
      "LIN_TIM": 75,
      "COR_NAM": "경기고속(일반)"
    },
    {
      "TIM_TIM": "1250",
      "LIN_TIM": 75,
      "COR_NAM": "대원고속(일반)"
    },
    {
      "TIM_TIM": "1500",
      "LIN_TIM": 75,
      "COR_NAM": "대원고속(일반)"
    },
    {
      "TIM_TIM": "1700",
      "LIN_TIM": 75,
      "COR_NAM": "경기고속(일반)"
    }
  ],
  "안성": [
    {
      "TIM_TIM": "0630",
      "LIN_TIM": 90,
      "COR_NAM": "대원고속(일반)"
    },
    {
      "TIM_TIM": "0800",
      "LIN_TIM": 90,
      "COR_NAM": "대원고속(일반)"
    },
    {
      "TIM_TIM": "1035",
      "LIN_TIM": 90,
      "COR_NAM": "대원고속(일반)"
    },
    {
      "TIM_TIM": "1300",
      "LIN_TIM": 100,
      "COR_NAM": "대원고속(일반)"
    },
    {
      "TIM_TIM": "1400",
      "LIN_TIM": 100,
      "COR_NAM": "대원고속(일반)"
    },
    {
      "TIM_TIM": "1620",
      "LIN_TIM": 100,
      "COR_NAM": "대원고속(일반)"
    },
    {
      "TIM_TIM": "1910",
      "LIN_TIM": 90,
      "COR_NAM": "대원고속(일반)"
    }
  ],
  "시민회관": [
    {
      "TIM_TIM": "0630",
      "LIN_TIM": 87,
      "COR_NAM": "대원고속(일반)"
    },
    {
      "TIM_TIM": "0800",
      "LIN_TIM": 87,
      "COR_NAM": "대원고속(일반)"
    },
    {
      "TIM_TIM": "1035",
      "LIN_TIM": 87,
      "COR_NAM": "대원고속(일반)"
    },
    {
      "TIM_TIM": "1910",
      "LIN_TIM": 87,
      "COR_NAM": "대원고속(일반)"
    }
  ],
  "대성리": [
    {
      "TIM_TIM": "0640",
      "LIN_TIM": 80,
      "COR_NAM": "강원고속(우등)"
    },
    {
      "TIM_TIM": "0840",
      "LIN_TIM": 80,
      "COR_NAM": "강원고속(우등)"
    },
    {
      "TIM_TIM": "1310",
      "LIN_TIM": 80,
      "COR_NAM": "강원고속(우등)"
    },
    {
      "TIM_TIM": "1510",
      "LIN_TIM": 80,
      "COR_NAM": "강원고속(우등)"
    },
    {
      "TIM_TIM": "1710",
      "LIN_TIM": 80,
      "COR_NAM": "강원고속(우등)"
    }
  ],
  "광교(중기센터)": [
    {
      "TIM_TIM": "0745",
      "LIN_TIM": 40,
      "COR_NAM": "경남여객(일반)"
    },
    {
      "TIM_TIM": "1300",
      "LIN_TIM": 40,
      "COR_NAM": "경남여객(일반)"
    },
    {
      "TIM_TIM": "1820",
      "LIN_TIM": 40,
      "COR_NAM": "경남여객(일반)"
    }
  ],
  "용인대": [
    {
      "TIM_TIM": "0745",
      "LIN_TIM": 95,
      "COR_NAM": "경남여객(일반)"
    },
    {
      "TIM_TIM": "1005",
      "LIN_TIM": 95,
      "COR_NAM": "경남여객(일반)"
    },
    {
      "TIM_TIM": "1300",
      "LIN_TIM": 95,
      "COR_NAM": "경남여객(일반)"
    },
    {
      "TIM_TIM": "1530",
      "LIN_TIM": 95,
      "COR_NAM": "경남여객(일반)"
    },
    {
      "TIM_TIM": "1820",
      "LIN_TIM": 95,
      "COR_NAM": "경남여객(일반)"
    },
    {
      "TIM_TIM": "2105",
      "LIN_TIM": 96,
      "COR_NAM": "경남여객(일반)"
    }
  ],
  "원동": [
    {
      "TIM_TIM": "0820",
      "LIN_TIM": 325,
      "COR_NAM": "경기고속(우등)"
    }
  ],
  "동광양(중마)": [
    {
      "TIM_TIM": "1500",
      "LIN_TIM": 290,
      "COR_NAM": "경기고속(우등)"
    }
  ],
  "통영": [
    {
      "TIM_TIM": "0720",
      "LIN_TIM": 280,
      "COR_NAM": "진안고속(우등)"
    },
    {
      "TIM_TIM": "1050",
      "LIN_TIM": 280,
      "COR_NAM": "진안고속(우등)"
    },
    {
      "TIM_TIM": "1220",
      "LIN_TIM": 280,
      "COR_NAM": "진안고속(우등)"
    },
    {
      "TIM_TIM": "1730",
      "LIN_TIM": 280,
      "COR_NAM": "진안고속(우등)"
    }
  ],
  "마산": [
    {
      "TIM_TIM": "0910",
      "LIN_TIM": 270,
      "COR_NAM": "대원고속(우등)"
    },
    {
      "TIM_TIM": "1300",
      "LIN_TIM": 270,
      "COR_NAM": "경남고속뉴부산관광(우등)"
    },
    {
      "TIM_TIM": "1600",
      "LIN_TIM": 270,
      "COR_NAM": "대원고속(우등)"
    },
    {
      "TIM_TIM": "1850",
      "LIN_TIM": 270,
      "COR_NAM": "경남고속뉴부산관광(우등)"
    },
    {
      "TIM_TIM": "2330",
      "LIN_TIM": 270,
      "COR_NAM": "천일여객(심야우등)"
    }
  ],
  "세종": [
    {
      "TIM_TIM": "0640",
      "LIN_TIM": 147,
      "COR_NAM": "금남고속(우등)"
    },
    {
      "TIM_TIM": "0820",
      "LIN_TIM": 125,
      "COR_NAM": "금남고속(우등)"
    },
    {
      "TIM_TIM": "1040",
      "LIN_TIM": 125,
      "COR_NAM": "중부고속(우등)"
    },
    {
      "TIM_TIM": "1540",
      "LIN_TIM": 125,
      "COR_NAM": "금남고속(우등)"
    },
    {
      "TIM_TIM": "1830",
      "LIN_TIM": 125,
      "COR_NAM": "중부고속(우등)"
    },
    {
      "TIM_TIM": "1930",
      "LIN_TIM": 120,
      "COR_NAM": "삼흥고속(우등)"
    }
  ],
  "해미": [
    {
      "TIM_TIM": "1050",
      "LIN_TIM": 91,
      "COR_NAM": "한양고속(우등)"
    },
    {
      "TIM_TIM": "1530",
      "LIN_TIM": 91,
      "COR_NAM": "충남고속(우등)"
    },
    {
      "TIM_TIM": "1645",
      "LIN_TIM": 91,
      "COR_NAM": "한양고속(우등)"
    },
    {
      "TIM_TIM": "2010",
      "LIN_TIM": 91,
      "COR_NAM": "충남고속(우등)"
    }
  ],
  "교통대": [
    {
      "TIM_TIM": "0805",
      "LIN_TIM": 135,
      "COR_NAM": "친선고속(일반)"
    },
    {
      "TIM_TIM": "1220",
      "LIN_TIM": 135,
      "COR_NAM": "친선고속(일반)"
    },
    {
      "TIM_TIM": "1730",
      "LIN_TIM": 135,
      "COR_NAM": "친선고속(일반)"
    }
  ],
  "건국대(충주)": [
    {
      "TIM_TIM": "0805",
      "LIN_TIM": 140,
      "COR_NAM": "친선고속(일반)"
    },
    {
      "TIM_TIM": "1220",
      "LIN_TIM": 140,
      "COR_NAM": "친선고속(일반)"
    },
    {
      "TIM_TIM": "1730",
      "LIN_TIM": 140,
      "COR_NAM": "친선고속(일반)"
    }
  ],
  "청주공항": [
    {
      "TIM_TIM": "0725",
      "LIN_TIM": 110,
      "COR_NAM": "금남고속(일반)"
    },
    {
      "TIM_TIM": "1600",
      "LIN_TIM": 110,
      "COR_NAM": "친선고속(일반)"
    }
  ],
  "군위": [
    {
      "TIM_TIM": "0850",
      "LIN_TIM": 303,
      "COR_NAM": "경북고속(우등)"
    },
    {
      "TIM_TIM": "1610",
      "LIN_TIM": 303,
      "COR_NAM": "경북고속(우등)"
    }
  ],
  "보령(대천)": [
    {
      "TIM_TIM": "0755",
      "LIN_TIM": 194,
      "COR_NAM": "충남고속(일반)"
    },
    {
      "TIM_TIM": "0900",
      "LIN_TIM": 130,
      "COR_NAM": "충남고속(우등)"
    },
    {
      "TIM_TIM": "1200",
      "LIN_TIM": 130,
      "COR_NAM": "충남고속(우등)"
    },
    {
      "TIM_TIM": "1550",
      "LIN_TIM": 130,
      "COR_NAM": "충남고속(우등)"
    },
    {
      "TIM_TIM": "1640",
      "LIN_TIM": 194,
      "COR_NAM": "충남고속(일반)"
    },
    {
      "TIM_TIM": "1745",
      "LIN_TIM": 130,
      "COR_NAM": "충남고속(일반)"
    },
    {
      "TIM_TIM": "1900",
      "LIN_TIM": 130,
      "COR_NAM": "충남고속(우등)"
    }
  ],
  "안동": [
    {
      "TIM_TIM": "0640",
      "LIN_TIM": 230,
      "COR_NAM": "경북고속(우등)"
    },
    {
      "TIM_TIM": "0745",
      "LIN_TIM": 244,
      "COR_NAM": "경북고속(우등)"
    },
    {
      "TIM_TIM": "0900",
      "LIN_TIM": 244,
      "COR_NAM": "경북고속(우등)"
    },
    {
      "TIM_TIM": "1120",
      "LIN_TIM": 244,
      "COR_NAM": "경북고속(우등)"
    },
    {
      "TIM_TIM": "1230",
      "LIN_TIM": 230,
      "COR_NAM": "경북고속(우등)"
    },
    {
      "TIM_TIM": "1455",
      "LIN_TIM": 244,
      "COR_NAM": "경북고속(우등)"
    },
    {
      "TIM_TIM": "1710",
      "LIN_TIM": 244,
      "COR_NAM": "경북고속(우등)"
    },
    {
      "TIM_TIM": "1830",
      "LIN_TIM": 244,
      "COR_NAM": "경북고속(우등)"
    },
    {
      "TIM_TIM": "1930",
      "LIN_TIM": 244,
      "COR_NAM": "경북고속(우등)"
    }
  ],
  "일직": [
    {
      "TIM_TIM": "0850",
      "LIN_TIM": 346,
      "COR_NAM": "경북고속(우등)"
    },
    {
      "TIM_TIM": "1610",
      "LIN_TIM": 346,
      "COR_NAM": "경북고속(우등)"
    }
  ],
  "용인": [
    {
      "TIM_TIM": "0745",
      "LIN_TIM": 110,
      "COR_NAM": "경남여객(일반)"
    },
    {
      "TIM_TIM": "1005",
      "LIN_TIM": 110,
      "COR_NAM": "경남여객(일반)"
    },
    {
      "TIM_TIM": "1300",
      "LIN_TIM": 110,
      "COR_NAM": "경남여객(일반)"
    },
    {
      "TIM_TIM": "1530",
      "LIN_TIM": 110,
      "COR_NAM": "경남여객(일반)"
    },
    {
      "TIM_TIM": "1820",
      "LIN_TIM": 110,
      "COR_NAM": "경남여객(일반)"
    },
    {
      "TIM_TIM": "2105",
      "LIN_TIM": 113,
      "COR_NAM": "경남여객(일반)"
    }
  ],
  "북대전IC": [
    {
      "TIM_TIM": "0610",
      "LIN_TIM": 115,
      "COR_NAM": "금남고속(우등)"
    },
    {
      "TIM_TIM": "0710",
      "LIN_TIM": 115,
      "COR_NAM": "금남고속(일반)"
    },
    {
      "TIM_TIM": "0940",
      "LIN_TIM": 115,
      "COR_NAM": "금남고속(우등)"
    },
    {
      "TIM_TIM": "1120",
      "LIN_TIM": 115,
      "COR_NAM": "금남고속(우등)"
    },
    {
      "TIM_TIM": "1300",
      "LIN_TIM": 115,
      "COR_NAM": "금남고속(우등)"
    },
    {
      "TIM_TIM": "1440",
      "LIN_TIM": 115,
      "COR_NAM": "금남고속(우등)"
    },
    {
      "TIM_TIM": "1615",
      "LIN_TIM": 115,
      "COR_NAM": "금남고속(우등)"
    },
    {
      "TIM_TIM": "1710",
      "LIN_TIM": 115,
      "COR_NAM": "금남고속(우등)"
    },
    {
      "TIM_TIM": "1850",
      "LIN_TIM": 115,
      "COR_NAM": "금남고속(우등)"
    },
    {
      "TIM_TIM": "2030",
      "LIN_TIM": 115,
      "COR_NAM": "금남고속(우등)"
    }
  ],
  "영월": [
    {
      "TIM_TIM": "0610",
      "LIN_TIM": 160,
      "COR_NAM": "경기고속(프리미엄)"
    },
    {
      "TIM_TIM": "1130",
      "LIN_TIM": 160,
      "COR_NAM": "경기고속(프리미엄)"
    },
    {
      "TIM_TIM": "1520",
      "LIN_TIM": 160,
      "COR_NAM": "경기고속(우등)"
    },
    {
      "TIM_TIM": "1750",
      "LIN_TIM": 160,
      "COR_NAM": "경기고속(프리미엄)"
    }
  ]
}